[{
    "speciesId": "swampert",
    "fastMove": "MUD_SHOT",
    "chargedMoves": ["HYDRO_CANNON", "EARTHQUAKE"],
    "weight": 20
}, {
    "speciesId": "trevenant",
    "weight": 18
}, {
    "speciesId": "walrein",
    "fastMove": "POWDER_SNOW",
    "chargedMoves": ["ICICLE_SPEAR", "EARTHQUAKE"],
    "weight": 15
}, {
    "speciesId": "ninetales_alolan",
    "fastMove": "POWDER_SNOW",
    "chargedMoves": ["WEATHER_BALL_ICE", "DAZZLING_GLEAM"],
    "weight": 12
}, {
    "speciesId": "ninetales_alolan_shadow",
    "fastMove": "POWDER_SNOW",
    "chargedMoves": ["WEATHER_BALL_ICE", "DAZZLING_GLEAM"]
}, {
    "speciesId": "stunfisk_galarian",
    "fastMove": "MUD_SHOT",
    "chargedMoves": ["ROCK_SLIDE", "EARTHQUAKE"],
    "weight": 12
}, {
    "speciesId": "pidgeot",
    "fastMove": "WING_ATTACK",
    "chargedMoves": ["FEATHER_DANCE", "BRAVE_BIRD"],
    "weight": 10
}, {
    "speciesId": "obstagoon",
    "fastMove": "COUNTER",
    "chargedMoves": ["NIGHT_SLASH", "CROSS_CHOP"],
    "weight": 10
}, {
    "speciesId": "venusaur",
    "fastMove": "VINE_WHIP",
    "chargedMoves": ["FRENZY_PLANT", "SLUDGE_BOMB"],
    "weight": 10
}, {
    "speciesId": "charizard",
    "fastMove": "WING_ATTACK",
    "chargedMoves": ["BLAST_BURN", "DRAGON_CLAW"],
    "weight": 9
}, {
    "speciesId": "drapion",
    "fastMove": "POISON_STING",
    "chargedMoves": ["CRUNCH", "AQUA_TAIL"],
    "weight": 8
}, {
    "speciesId": "mandibuzz",
    "weight": 8
}, {
    "speciesId": "scrafty",
    "fastMove": "COUNTER",
    "chargedMoves": ["FOUL_PLAY", "POWER_UP_PUNCH"],
    "weight": 8
}, {
    "speciesId": "abomasnow",
    "weight": 7
}, {
    "speciesId": "dragonite",
    "weight": 7
}, {
    "speciesId": "machamp_shadow",
    "fastMove": "COUNTER",
    "chargedMoves": ["CROSS_CHOP", "ROCK_SLIDE"],
    "weight": 7
}, {
    "speciesId": "jellicent",
    "fastMove": "HEX",
    "chargedMoves": ["BUBBLE_BEAM", "SHADOW_BALL"],
    "weight": 6
}, {
    "speciesId": "talonflame",
    "fastMove": "INCINERATE",
    "chargedMoves": ["BRAVE_BIRD", "FLAME_CHARGE"],
    "weight": 6
}, {
    "speciesId": "umbreon",
    "chargedMoves": ["FOUL_PLAY", "LAST_RESORT"],
    "weight": 6
}, {
    "speciesId": "empoleon",
    "fastMove": "WATERFALL",
    "chargedMoves": ["HYDRO_CANNON", "DRILL_PECK"],
    "weight": 5
}, {
    "speciesId": "escavalier",
    "fastMove": "COUNTER",
    "chargedMoves": ["DRILL_RUN", "MEGAHORN"],
    "weight": 5
}, {
    "speciesId": "snorlax",
    "fastMove": "LICK",
    "chargedMoves": ["BODY_SLAM", "SUPER_POWER"],
    "weight": 4
}, {
    "speciesId": "kingdra",
    "fastMove": "DRAGON_BREATH",
    "chargedMoves": ["OUTRAGE", "OCTAZOOKA"],
    "weight": 4
}, {
    "speciesId": "charizard_shadow",
    "fastMove": "WING_ATTACK",
    "chargedMoves": ["BLAST_BURN", "DRAGON_CLAW"],
    "weight": 4
}, {
    "speciesId": "ferrothorn",
    "fastMove": "BULLET_SEED",
    "chargedMoves": ["POWER_WHIP", "FLASH_CANNON"],
    "weight": 4
}, {
    "speciesId": "gallade",
    "fastMove": "CONFUSION",
    "chargedMoves": ["CLOSE_COMBAT", "LEAF_BLADE"],
    "weight": 4
}, {
    "speciesId": "galvantula",
    "weight": 4
}, {
    "speciesId": "greedent",
    "fastMove": "TACKLE",
    "weight": 4
}, {
    "speciesId": "machamp",
    "fastMove": "COUNTER",
    "chargedMoves": ["CROSS_CHOP", "ROCK_SLIDE"],
    "weight": 4
}, {
    "speciesId": "muk_alolan",
    "fastMove": "POISON_JAB",
    "chargedMoves": ["DARK_PULSE", "ACID_SPRAY"],
    "weight": 4
}, {
    "speciesId": "sirfetchd",
    "chargedMoves": ["LEAF_BLADE", "BRAVE_BIRD"],
    "weight": 4
}, {
    "speciesId": "toxicroak",
    "chargedMoves": ["MUD_BOMB", "SLUDGE_BOMB"],
    "weight": 4
}, {
    "speciesId": "dragalge",
    "weight": 3
}, {
    "speciesId": "drifblim",
    "weight": 3
}, {
    "speciesId": "gyarados",
    "weight": 3
}, {
    "speciesId": "ninetales",
    "fastMove": "FIRE_SPIN",
    "chargedMoves": ["OVERHEAT", "WEATHER_BALL_FIRE"],
    "weight": 3
}, {
    "speciesId": "roserade",
    "chargedMoves": ["WEATHER_BALL_FIRE", "LEAF_STORM"],
    "weight": 3
}, {
    "speciesId": "steelix",
    "fastMove": "DRAGON_TAIL",
    "chargedMoves": ["PSYCHIC_FANGS", "CRUNCH"],
    "weight": 3
}, {
    "speciesId": "lanturn",
    "fastMove": "SPARK",
    "chargedMoves": ["SURF", "THUNDERBOLT"],
    "weight": 3
}, {
    "speciesId": "aurorus",
    "fastMove": "POWDER_SNOW",
    "chargedMoves": ["WEATHER_BALL_ICE", "METEOR_BEAM"],
    "weight": 2
}, {
    "speciesId": "dragonite_shadow",
    "weight": 2
}, {
    "speciesId": "gengar",
    "chargedMoves": ["SHADOW_PUNCH", "SLUDGE_BOMB"],
    "weight": 2
}, {
    "speciesId": "granbull",
    "fastMove": "CHARM",
    "weight": 2
}, {
    "speciesId": "lapras",
    "chargedMoves": ["SURF", "SKULL_BASH"],
    "weight": 2
}, {
    "speciesId": "magnezone",
    "weight": 2
}, {
    "speciesId": "nidoqueen",
    "fastMove": "POISON_JAB",
    "chargedMoves": ["EARTH_POWER", "POISON_FANG"],
    "weight": 2
}, {
    "speciesId": "politoed",
    "chargedMoves": ["WEATHER_BALL_WATER", "EARTHQUAKE"],
    "weight": 2
}, {
    "speciesId": "snorlax_shadow",
    "weight": 2
}, {
    "speciesId": "swampert_shadow",
    "chargedMoves": ["HYDRO_CANNON", "EARTHQUAKE"],
    "weight": 2
}, {
    "speciesId": "pelipper",
    "fastMove": "WING_ATTACK",
    "chargedMoves": ["WEATHER_BALL_WATER", "HURRICANE"],
    "weight": 2
}, {
    "speciesId": "blastoise",
    "chargedMoves": ["HYDRO_CANNON", "SKULL_BASH"],
    "weight": 1
}, {
    "speciesId": "blaziken",
    "fastMove": "COUNTER",
    "chargedMoves": ["BLAZE_KICK", "STONE_EDGE"],
    "weight": 1
}, {
    "speciesId": "bouffalant",
    "chargedMoves": ["STOMP", "SKULL_BASH"],
    "weight": 1
}, {
    "speciesId": "breloom",
    "chargedMoves": ["SEED_BOMB", "SLUDGE_BOMB"],
    "weight": 1
}, {
    "speciesId": "bronzong",
    "chargedMoves": ["PSYSHOCK", "PAYBACK"],
    "weight": 1
}, {
    "speciesId": "clefable",
    "fastMove": "CHARM",
    "chargedMoves": ["METEOR_MASH", "MOONBLAST"],
    "weight": 1
}, {
    "speciesId": "cloyster",
    "chargedMoves": ["ICY_WIND", "HYDRO_PUMP"],
    "weight": 1
}, {
    "speciesId": "crobat",
    "fastMove": "AIR_SLASH",
    "chargedMoves": ["POISON_FANG", "SHADOW_BALL"],
    "weight": 1
}, {
    "speciesId": "crobat_shadow",
    "chargedMoves": ["POISON_FANG", "SHADOW_BALL"],
    "weight": 1
}, {
    "speciesId": "crustle",
    "fastMove": "SMACK_DOWN",
    "weight": 1
}, {
    "speciesId": "crustle",
    "fastMove": "SMACK_DOWN",
    "weight": 1
}, {
    "speciesId": "dewgong",
    "chargedMoves": ["ICY_WIND", "WATER_PULSE"],
    "weight": 1
}, {
    "speciesId": "dewgong",
    "chargedMoves": ["ICY_WIND", "WATER_PULSE"],
    "weight": 1
}, {
    "speciesId": "dubwool",
    "chargedMoves": ["BODY_SLAM", "PAYBACK"],
    "weight": 1
}, {
    "speciesId": "electrode",
    "chargedMoves": ["DISCHARGE", "HYPER_BEAM"],
    "weight": 1
}, {
    "speciesId": "exeggutor",
    "fastMove": "CONFUSION",
    "weight": 1
}, {
    "speciesId": "exeggutor_shadow",
    "fastMove": "CONFUSION",
    "chargedMoves": ["SEED_BOMB", "PSYCHIC"],
    "weight": 1
}, {
    "speciesId": "falinks",
    "chargedMoves": ["SUPER_POWER", "MEGAHORN"],
    "weight": 1
}, {
    "speciesId": "feraligatr",
    "fastMove": "WATERFALL",
    "weight": 1
}, {
    "speciesId": "ferrothorn",
    "chargedMoves": ["POWER_WHIP", "FLASH_CANNON"],
    "weight": 1
}, {
    "speciesId": "flygon_shadow",
    "fastMove": "DRAGON_TAIL",
    "weight": 1
}, {
    "speciesId": "forretress",
    "chargedMoves": ["MIRROR_SHOT", "EARTHQUAKE"],
    "weight": 1
}, {
    "speciesId": "forretress_shadow",
    "chargedMoves": ["MIRROR_SHOT", "EARTHQUAKE"],
    "weight": 1
}, {
    "speciesId": "gliscor",
    "fastMove": "WING_ATTACK",
    "chargedMoves": ["NIGHT_SLASH", "EARTHQUAKE"],
    "weight": 1
}, {
    "speciesId": "gliscor_shadow",
    "fastMove": "WING_ATTACK",
    "chargedMoves": ["NIGHT_SLASH", "EARTHQUAKE"],
    "weight": 1
}, {
    "speciesId": "golem_alolan",
    "fastMove": "VOLT_SWITCH",
    "chargedMoves": ["ROCK_BLAST", "STONE_EDGE"],
    "weight": 1
}, {
    "speciesId": "granbull_shadow",
    "fastMove": "CHARM",
    "weight": 1
}, {
    "speciesId": "hariyama",
    "chargedMoves": ["CLOSE_COMBAT", "HEAVY_SLAM"],
    "weight": 1
}, {
    "speciesId": "hariyama_shadow",
    "chargedMoves": ["CLOSE_COMBAT", "HEAVY_SLAM"],
    "weight": 1
}, {
    "speciesId": "heracross",
    "chargedMoves": ["ROCK_BLAST", "MEGAHORN"],
    "weight": 1
}, {
    "speciesId": "hippowdon",
    "chargedMoves": ["WEATHER_BALL_ROCK", "EARTH_POWER"],
    "weight": 1
}, {
    "speciesId": "hitmonchan",
    "chargedMoves": ["ICE_PUNCH", "THUNDER_PUNCH"],
    "weight": 1
}, {
    "speciesId": "hitmonchan",
    "chargedMoves": ["ICE_PUNCH", "THUNDER_PUNCH"],
    "weight": 1
}, {
    "speciesId": "hitmonchan_shadow",
    "chargedMoves": ["ICE_PUNCH", "THUNDER_PUNCH"],
    "weight": 1
}, {
    "speciesId": "hypno",
    "chargedMoves": ["THUNDER_PUNCH", "SHADOW_BALL"],
    "weight": 1
}, {
    "speciesId": "hypno",
    "chargedMoves": ["THUNDER_PUNCH", "SHADOW_BALL"],
    "weight": 1
}, {
    "speciesId": "hypno_shadow",
    "chargedMoves": ["THUNDER_PUNCH", "FIRE_PUNCH"],
    "weight": 1
}, {
    "speciesId": "hypno_shadow",
    "chargedMoves": ["THUNDER_PUNCH", "FIRE_PUNCH"],
    "weight": 1
}, {
    "speciesId": "lapras",
    "chargedMoves": ["SURF", "SKULL_BASH"],
    "weight": 1
}, {
    "speciesId": "lapras_shadow",
    "chargedMoves": ["SURF", "SKULL_BASH"],
    "weight": 1
}, {
    "speciesId": "leavanny",
    "fastMove": "RAZOR_LEAF",
    "weight": 1
}, {
    "speciesId": "lucario",
    "chargedMoves": ["POWER_UP_PUNCH", "SHADOW_BALL"],
    "weight": 1
}, {
    "speciesId": "ludicolo",
    "chargedMoves": ["ICE_BEAM", "LEAF_STORM"],
    "weight": 1
}, {
    "speciesId": "magmortar",
    "chargedMoves": ["FIRE_PUNCH", "THUNDERBOLT"],
    "weight": 1
}, {
    "speciesId": "magmortar_shadow",
    "chargedMoves": ["FIRE_PUNCH", "THUNDERBOLT"],
    "weight": 1
}, {
    "speciesId": "mantine",
    "chargedMoves": ["BUBBLE_BEAM", "ICE_BEAM"],
    "weight": 1
}, {
    "speciesId": "miltank",
    "fastMove": "TACKLE",
    "weight": 1
}, {
    "speciesId": "mr_rime",
    "fastMove": "CONFUSION",
    "chargedMoves": ["ICY_WIND", "PSYCHIC"],
    "weight": 1
}, {
    "speciesId": "nidoqueen_shadow",
    "fastMove": "POISON_JAB",
    "chargedMoves": ["EARTH_POWER", "POISON_FANG"],
    "weight": 1
}, {
    "speciesId": "ninetales_shadow",
    "fastMove": "EMBER",
    "chargedMoves": ["WEATHER_BALL_FIRE", "OVERHEAT"],
    "weight": 1
}, {
    "speciesId": "overqwil",
    "chargedMoves": ["AQUA_TAIL", "SHADOW_BALL"],
    "weight": 1
}, {
    "speciesId": "politoed_shadow",
    "chargedMoves": ["WEATHER_BALL_WATER", "EARTHQUAKE"],
    "weight": 1
}, {
    "speciesId": "poliwrath",
    "chargedMoves": ["ICE_PUNCH", "DYNAMIC_PUNCH"],
    "weight": 1
}, {
    "speciesId": "poliwrath_shadow",
    "chargedMoves": ["ICE_PUNCH", "DYNAMIC_PUNCH"],
    "weight": 1
}, {
    "speciesId": "porygon_z",
    "chargedMoves": ["TRI_ATTACK", "RETURN"],
    "weight": 1
}, {
    "speciesId": "porygon_z_shadow",
    "chargedMoves": ["TRI_ATTACK", "BLIZZARD"],
    "weight": 1
}, {
    "speciesId": "primeape",
    "fastMove": "COUNTER",
    "chargedMoves": ["NIGHT_SLASH", "ICE_PUNCH"],
    "weight": 1
}, {
    "speciesId": "probopass",
    "chargedMoves": ["ROCK_SLIDE", "THUNDERBOLT"],
    "weight": 1
}, {
    "speciesId": "qwilfish_hisuian",
    "chargedMoves": ["AQUA_TAIL", "SHADOW_BALL"],
    "weight": 1
}, {
    "speciesId": "rapidash_galarian",
    "fastMove": "FAIRY_WIND",
    "chargedMoves": ["BODY_SLAM", "HIGH_HORSEPOWER"],
    "weight": 1
}, {
    "speciesId": "runerigus",
    "chargedMoves": ["SAND_TOMB", "SHADOW_BALL"],
    "weight": 1
}, {
    "speciesId": "sandslash_alolan",
    "chargedMoves": ["ICE_PUNCH", "BULLDOZE"],
    "weight": 1
}, {
    "speciesId": "sceptile",
    "chargedMoves": ["LEAF_BLADE", "EARTHQUAKE"],
    "weight": 1
}, {
    "speciesId": "scizor",
    "fastMove": "BULLET_PUNCH",
    "chargedMoves": ["NIGHT_SLASH", "IRON_HEAD"],
    "weight": 1
}, {
    "speciesId": "scizor_shadow",
    "fastMove": "BULLET_PUNCH",
    "chargedMoves": ["NIGHT_SLASH", "IRON_HEAD"],
    "weight": 1
}, {
    "speciesId": "serperior",
    "chargedMoves": ["FRENZY_PLANT", "AERIAL_ACE"],
    "weight": 1
}, {
    "speciesId": "skuntank",
    "chargedMoves": ["CRUNCH", "FLAMETHROWER"],
    "weight": 1
}, {
    "speciesId": "skuntank_shadow",
    "chargedMoves": ["CRUNCH", "FLAMETHROWER"],
    "weight": 1
}, {
    "speciesId": "slowbro_galarian",
    "chargedMoves": ["SLUDGE_BOMB", "FOCUS_BLAST"],
    "weight": 1
}, {
    "speciesId": "tentacruel",
    "chargedMoves": ["SCALD", "SLUDGE_WAVE"],
    "weight": 1
}, {
    "speciesId": "togekiss",
    "fastMove": "CHARM",
    "chargedMoves": ["ANCIENT_POWER", "FLAMETHROWER"],
    "weight": 1
}, {
    "speciesId": "weezing_galarian",
    "chargedMoves": ["PLAY_ROUGH", "OVERHEAT"],
    "weight": 1
}]
