[{"speciesId":"aerodactyl","speciesName":"Aerodactyl","rating":500,"matchups":[],"counters":[],"moves":{"fastMoves":[{"moveId":"ROCK_THROW","uses":9530},{"moveId":"STEEL_WING","uses":4609},{"moveId":"BITE","uses":4567}],"chargedMoves":[{"moveId":"ROCK_SLIDE","uses":7467},{"moveId":"EARTH_POWER","uses":4394},{"moveId":"IRON_HEAD","uses":2443},{"moveId":"RETURN","uses":1933},{"moveId":"ANCIENT_POWER","uses":1723},{"moveId":"HYPER_BEAM","uses":749}]},"moveset":["BITE","ANCIENT_POWER","EARTH_POWER"],"score":100},{"speciesId":"aggron","speciesName":"Aggron","rating":500,"matchups":[],"counters":[],"moves":{"fastMoves":[{"moveId":"SMACK_DOWN","uses":9114},{"moveId":"DRAGON_TAIL","uses":7094},{"moveId":"IRON_TAIL","uses":2491}],"chargedMoves":[{"moveId":"STONE_EDGE","uses":7876},{"moveId":"HEAVY_SLAM","uses":4671},{"moveId":"THUNDER","uses":3534},{"moveId":"RETURN","uses":2621}]},"moveset":["DRAGON_TAIL","HEAVY_SLAM","RETURN"],"score":100},{"speciesId":"alakazam","speciesName":"Alakazam","rating":500,"matchups":[],"counters":[],"moves":{"fastMoves":[{"moveId":"COUNTER","uses":7198},{"moveId":"PSYCHO_CUT","uses":6195},{"moveId":"CONFUSION","uses":5316}],"chargedMoves":[{"moveId":"FIRE_PUNCH","uses":4111},{"moveId":"PSYCHIC","uses":3756},{"moveId":"SHADOW_BALL","uses":3553},{"moveId":"FOCUS_BLAST","uses":2422},{"moveId":"RETURN","uses":1747},{"moveId":"FUTURE_SIGHT","uses":1640},{"moveId":"DAZZLING_GLEAM","uses":1479}]},"moveset":["CONFUSION","DAZZLING_GLEAM","FIRE_PUNCH"],"score":100},{"speciesId":"alomomola","speciesName":"Alomomola","rating":500,"matchups":[],"counters":[],"moves":{"fastMoves":[{"moveId":"WATERFALL","uses":2032},{"moveId":"HIDDEN_POWER_WATER","uses":1384},{"moveId":"HIDDEN_POWER_GROUND","uses":1164},{"moveId":"HIDDEN_POWER_ROCK","uses":1164},{"moveId":"HIDDEN_POWER_FIRE","uses":1122},{"moveId":"HIDDEN_POWER_ICE","uses":1094},{"moveId":"HIDDEN_POWER_FIGHTING","uses":1075},{"moveId":"HIDDEN_POWER_ELECTRIC","uses":1052},{"moveId":"HIDDEN_POWER_FLYING","uses":1048},{"moveId":"HIDDEN_POWER_DARK","uses":1014},{"moveId":"HIDDEN_POWER_GHOST","uses":1009},{"moveId":"HIDDEN_POWER_GRASS","uses":987},{"moveId":"HIDDEN_POWER_PSYCHIC","uses":934},{"moveId":"HIDDEN_POWER_BUG","uses":923},{"moveId":"HIDDEN_POWER_DRAGON","uses":911},{"moveId":"HIDDEN_POWER_STEEL","uses":875},{"moveId":"HIDDEN_POWER_POISON","uses":857}],"chargedMoves":[{"moveId":"HYDRO_PUMP","uses":6739},{"moveId":"PSYCHIC","uses":6639},{"moveId":"BLIZZARD","uses":5324}]},"moveset":["HIDDEN_POWER_BUG","BLIZZARD","HYDRO_PUMP"],"score":100},{"speciesId":"amoonguss","speciesName":"Amoonguss","rating":500,"matchups":[],"counters":[],"moves":{"fastMoves":[{"moveId":"FEINT_ATTACK","uses":12997},{"moveId":"ASTONISH","uses":5703}],"chargedMoves":[{"moveId":"GRASS_KNOT","uses":7308},{"moveId":"FOUL_PLAY","uses":5737},{"moveId":"SLUDGE_BOMB","uses":5654}]},"moveset":["ASTONISH","FOUL_PLAY","GRASS_KNOT"],"score":100},{"speciesId":"ampharos","speciesName":"Ampharos","rating":500,"matchups":[],"counters":[],"moves":{"fastMoves":[{"moveId":"VOLT_SWITCH","uses":12803},{"moveId":"CHARGE_BEAM","uses":5897}],"chargedMoves":[{"moveId":"THUNDER_PUNCH","uses":5740},{"moveId":"FOCUS_BLAST","uses":3001},{"moveId":"DRAGON_PULSE","uses":2262},{"moveId":"RETURN","uses":2250},{"moveId":"POWER_GEM","uses":2242},{"moveId":"THUNDER","uses":1851},{"moveId":"ZAP_CANNON","uses":1313}]},"moveset":["CHARGE_BEAM","DRAGON_PULSE","FOCUS_BLAST"],"score":100},{"speciesId":"arcanine","speciesName":"Arcanine","rating":500,"matchups":[],"counters":[],"moves":{"fastMoves":[{"moveId":"SNARL","uses":7128},{"moveId":"FIRE_FANG","uses":5313},{"moveId":"THUNDER_FANG","uses":3821},{"moveId":"BITE","uses":2447}],"chargedMoves":[{"moveId":"WILD_CHARGE","uses":6617},{"moveId":"FLAMETHROWER","uses":4063},{"moveId":"CRUNCH","uses":3374},{"moveId":"BULLDOZE","uses":2012},{"moveId":"RETURN","uses":1550},{"moveId":"FIRE_BLAST","uses":1091}]},"moveset":["BITE","BULLDOZE","CRUNCH"],"score":100},{"speciesId":"archeops","speciesName":"Archeops","rating":500,"matchups":[],"counters":[],"moves":{"fastMoves":[{"moveId":"WING_ATTACK","uses":12171},{"moveId":"STEEL_WING","uses":6529}],"chargedMoves":[{"moveId":"DRAGON_CLAW","uses":7297},{"moveId":"CRUNCH","uses":6061},{"moveId":"ANCIENT_POWER","uses":5336}]},"moveset":["STEEL_WING","ANCIENT_POWER","CRUNCH"],"score":100},{"speciesId":"armaldo","speciesName":"Armaldo","rating":500,"matchups":[],"counters":[],"moves":{"fastMoves":[{"moveId":"FURY_CUTTER","uses":12316},{"moveId":"STRUGGLE_BUG","uses":6384}],"chargedMoves":[{"moveId":"ROCK_BLAST","uses":9970},{"moveId":"CROSS_POISON","uses":5459},{"moveId":"WATER_PULSE","uses":3282}]},"moveset":["FURY_CUTTER","CROSS_POISON","ROCK_BLAST"],"score":100},{"speciesId":"banette","speciesName":"Banette","rating":500,"matchups":[],"counters":[],"moves":{"fastMoves":[{"moveId":"SHADOW_CLAW","uses":11191},{"moveId":"HEX","uses":7509}],"chargedMoves":[{"moveId":"SHADOW_BALL","uses":8493},{"moveId":"THUNDER","uses":4456},{"moveId":"RETURN","uses":3159},{"moveId":"DAZZLING_GLEAM","uses":2608}]},"moveset":["HEX","DAZZLING_GLEAM","RETURN"],"score":100},{"speciesId":"beartic","speciesName":"Beartic","rating":500,"matchups":[],"counters":[],"moves":{"fastMoves":[{"moveId":"POWDER_SNOW","uses":12798},{"moveId":"CHARM","uses":5902}],"chargedMoves":[{"moveId":"SURF","uses":8061},{"moveId":"ICE_PUNCH","uses":7809},{"moveId":"PLAY_ROUGH","uses":2829}]},"moveset":["CHARM","ICE_PUNCH","PLAY_ROUGH"],"score":100},{"speciesId":"bellossom","speciesName":"Bellossom","rating":500,"matchups":[],"counters":[],"moves":{"fastMoves":[{"moveId":"BULLET_SEED","uses":9575},{"moveId":"RAZOR_LEAF","uses":5574},{"moveId":"ACID","uses":3557}],"chargedMoves":[{"moveId":"LEAF_BLADE","uses":12903},{"moveId":"RETURN","uses":2597},{"moveId":"DAZZLING_GLEAM","uses":1906},{"moveId":"PETAL_BLIZZARD","uses":1354}]},"moveset":["ACID","DAZZLING_GLEAM","LEAF_BLADE"],"score":100},{"speciesId":"bisharp","speciesName":"Bisharp","rating":500,"matchups":[],"counters":[],"moves":{"fastMoves":[{"moveId":"SNARL","uses":12263},{"moveId":"METAL_CLAW","uses":6437}],"chargedMoves":[{"moveId":"DARK_PULSE","uses":6427},{"moveId":"X_SCISSOR","uses":5011},{"moveId":"IRON_HEAD","uses":4135},{"moveId":"FOCUS_BLAST","uses":3137}]},"moveset":["METAL_CLAW","DARK_PULSE","FOCUS_BLAST"],"score":100},{"speciesId":"blastoise","speciesName":"Blastoise","rating":500,"matchups":[],"counters":[],"moves":{"fastMoves":[{"moveId":"WATER_GUN","uses":12919},{"moveId":"BITE","uses":5781}],"chargedMoves":[{"moveId":"HYDRO_CANNON","uses":9780},{"moveId":"ICE_BEAM","uses":2944},{"moveId":"SKULL_BASH","uses":2008},{"moveId":"RETURN","uses":1688},{"moveId":"FLASH_CANNON","uses":1236},{"moveId":"HYDRO_PUMP","uses":1059}]},"moveset":["BITE","FLASH_CANNON","HYDRO_CANNON"],"score":100},{"speciesId":"blaziken","speciesName":"Blaziken","rating":500,"matchups":[],"counters":[],"moves":{"fastMoves":[{"moveId":"COUNTER","uses":11390},{"moveId":"FIRE_SPIN","uses":7310}],"chargedMoves":[{"moveId":"BLAST_BURN","uses":5219},{"moveId":"BRAVE_BIRD","uses":3821},{"moveId":"BLAZE_KICK","uses":3211},{"moveId":"STONE_EDGE","uses":3003},{"moveId":"FOCUS_BLAST","uses":2340},{"moveId":"OVERHEAT","uses":1116}]},"moveset":["COUNTER","BLAST_BURN","BLAZE_KICK"],"score":100},{"speciesId":"braviary","speciesName":"Braviary","rating":500,"matchups":[],"counters":[],"moves":{"fastMoves":[{"moveId":"AIR_SLASH","uses":12923},{"moveId":"STEEL_WING","uses":5777}],"chargedMoves":[{"moveId":"BRAVE_BIRD","uses":6870},{"moveId":"CLOSE_COMBAT","uses":6653},{"moveId":"ROCK_SLIDE","uses":4339},{"moveId":"HEAT_WAVE","uses":826}]},"moveset":["AIR_SLASH","BRAVE_BIRD","CLOSE_COMBAT"],"score":100},{"speciesId":"breloom","speciesName":"Breloom","rating":500,"matchups":[],"counters":[],"moves":{"fastMoves":[{"moveId":"COUNTER","uses":10819},{"moveId":"BULLET_SEED","uses":7881}],"chargedMoves":[{"moveId":"DYNAMIC_PUNCH","uses":6111},{"moveId":"GRASS_KNOT","uses":4779},{"moveId":"SEED_BOMB","uses":4381},{"moveId":"SLUDGE_BOMB","uses":3440}]},"moveset":["BULLET_SEED","DYNAMIC_PUNCH","GRASS_KNOT"],"score":100},{"speciesId":"bronzong","speciesName":"Bronzong","rating":500,"matchups":[],"counters":[],"moves":{"fastMoves":[{"moveId":"CONFUSION","uses":11108},{"moveId":"FEINT_ATTACK","uses":7592}],"chargedMoves":[{"moveId":"PSYSHOCK","uses":6797},{"moveId":"HEAVY_SLAM","uses":4561},{"moveId":"BULLDOZE","uses":3251},{"moveId":"PSYCHIC","uses":2631},{"moveId":"FLASH_CANNON","uses":1429}]},"moveset":["CONFUSION","BULLDOZE","FLASH_CANNON"],"score":100},{"speciesId":"camerupt","speciesName":"Camerupt","rating":500,"matchups":[],"counters":[],"moves":{"fastMoves":[{"moveId":"EMBER","uses":14450},{"moveId":"ROCK_SMASH","uses":4250}],"chargedMoves":[{"moveId":"OVERHEAT","uses":6593},{"moveId":"EARTH_POWER","uses":6513},{"moveId":"EARTHQUAKE","uses":2825},{"moveId":"SOLAR_BEAM","uses":2762}]},"moveset":["EMBER","EARTHQUAKE","EARTH_POWER"],"score":100},{"speciesId":"carracosta","speciesName":"Carracosta","rating":500,"matchups":[],"counters":[],"moves":{"fastMoves":[{"moveId":"WATER_GUN","uses":9473},{"moveId":"ROCK_THROW","uses":9227}],"chargedMoves":[{"moveId":"SURF","uses":8270},{"moveId":"BODY_SLAM","uses":6630},{"moveId":"ANCIENT_POWER","uses":3811}]},"moveset":["ROCK_THROW","ANCIENT_POWER","BODY_SLAM"],"score":100},{"speciesId":"celebi","speciesName":"Celebi","rating":500,"matchups":[],"counters":[],"moves":{"fastMoves":[{"moveId":"CONFUSION","uses":11835},{"moveId":"CHARGE_BEAM","uses":6865}],"chargedMoves":[{"moveId":"SEED_BOMB","uses":7637},{"moveId":"PSYCHIC","uses":6303},{"moveId":"DAZZLING_GLEAM","uses":2404},{"moveId":"HYPER_BEAM","uses":2324}]},"moveset":["CHARGE_BEAM","DAZZLING_GLEAM","HYPER_BEAM"],"score":100},{"speciesId":"chandelure","speciesName":"Chandelure","rating":500,"matchups":[],"counters":[],"moves":{"fastMoves":[{"moveId":"INCINERATE","uses":8312},{"moveId":"HEX","uses":5526},{"moveId":"FIRE_SPIN","uses":4872}],"chargedMoves":[{"moveId":"SHADOW_BALL","uses":5441},{"moveId":"FLAME_CHARGE","uses":5369},{"moveId":"OVERHEAT","uses":4149},{"moveId":"ENERGY_BALL","uses":3711}]},"moveset":["FIRE_SPIN","ENERGY_BALL","FLAME_CHARGE"],"score":100},{"speciesId":"charizard","speciesName":"Charizard","rating":500,"matchups":[],"counters":[],"moves":{"fastMoves":[{"moveId":"FIRE_SPIN","uses":4146},{"moveId":"EMBER","uses":3871},{"moveId":"WING_ATTACK","uses":3836},{"moveId":"DRAGON_BREATH","uses":3820},{"moveId":"AIR_SLASH","uses":3009}],"chargedMoves":[{"moveId":"BLAST_BURN","uses":7630},{"moveId":"DRAGON_CLAW","uses":5021},{"moveId":"FLAMETHROWER","uses":1740},{"moveId":"RETURN","uses":1721},{"moveId":"OVERHEAT","uses":1633},{"moveId":"FIRE_BLAST","uses":923}]},"moveset":["AIR_SLASH","BLAST_BURN","DRAGON_CLAW"],"score":100},{"speciesId":"cherrim_sunny","speciesName":"Cherrim (Sunshine)","rating":500,"matchups":[],"counters":[],"moves":{"fastMoves":[{"moveId":"BULLET_SEED","uses":11842},{"moveId":"RAZOR_LEAF","uses":6858}],"chargedMoves":[{"moveId":"WEATHER_BALL_FIRE","uses":10557},{"moveId":"SOLAR_BEAM","uses":4000},{"moveId":"DAZZLING_GLEAM","uses":2117},{"moveId":"HYPER_BEAM","uses":2049}]},"moveset":["BULLET_SEED","DAZZLING_GLEAM","HYPER_BEAM"],"score":100},{"speciesId":"chesnaught","speciesName":"Chesnaught","rating":500,"matchups":[],"counters":[],"moves":{"fastMoves":[{"moveId":"VINE_WHIP","uses":10719},{"moveId":"SMACK_DOWN","uses":6063},{"moveId":"LOW_KICK","uses":1927}],"chargedMoves":[{"moveId":"SUPER_POWER","uses":10190},{"moveId":"ENERGY_BALL","uses":4843},{"moveId":"GYRO_BALL","uses":2236},{"moveId":"SOLAR_BEAM","uses":1413}]},"moveset":["LOW_KICK","ENERGY_BALL","GYRO_BALL"],"score":100},{"speciesId":"cinccino","speciesName":"Cinccino","rating":500,"matchups":[],"counters":[],"moves":{"fastMoves":[{"moveId":"CHARM","uses":14124},{"moveId":"POUND","uses":4576}],"chargedMoves":[{"moveId":"AQUA_TAIL","uses":9626},{"moveId":"THUNDERBOLT","uses":5295},{"moveId":"HYPER_BEAM","uses":3765}]},"moveset":["CHARM","AQUA_TAIL","HYPER_BEAM"],"score":100},{"speciesId":"claydol","speciesName":"Claydol","rating":500,"matchups":[],"counters":[],"moves":{"fastMoves":[{"moveId":"CONFUSION","uses":6900},{"moveId":"MUD_SLAP","uses":6161},{"moveId":"EXTRASENSORY","uses":5630}],"chargedMoves":[{"moveId":"EARTH_POWER","uses":4849},{"moveId":"PSYCHIC","uses":3690},{"moveId":"SHADOW_BALL","uses":3352},{"moveId":"ICE_BEAM","uses":3331},{"moveId":"EARTHQUAKE","uses":2094},{"moveId":"GYRO_BALL","uses":1373}]},"moveset":["CONFUSION","EARTHQUAKE","EARTH_POWER"],"score":100},{"speciesId":"cloyster","speciesName":"Cloyster","rating":500,"matchups":[],"counters":[],"moves":{"fastMoves":[{"moveId":"ICE_SHARD","uses":11498},{"moveId":"FROST_BREATH","uses":7202}],"chargedMoves":[{"moveId":"AVALANCHE","uses":8283},{"moveId":"HYDRO_PUMP","uses":3188},{"moveId":"ICY_WIND","uses":2897},{"moveId":"RETURN","uses":2033},{"moveId":"BLIZZARD","uses":1284},{"moveId":"AURORA_BEAM","uses":1036}]},"moveset":["FROST_BREATH","AURORA_BEAM","AVALANCHE"],"score":100},{"speciesId":"cradily","speciesName":"Cradily","rating":500,"matchups":[],"counters":[],"moves":{"fastMoves":[{"moveId":"BULLET_SEED","uses":9037},{"moveId":"INFESTATION","uses":7074},{"moveId":"ACID","uses":2594}],"chargedMoves":[{"moveId":"STONE_EDGE","uses":7365},{"moveId":"GRASS_KNOT","uses":6497},{"moveId":"BULLDOZE","uses":2657},{"moveId":"RETURN","uses":2182}]},"moveset":["ACID","BULLDOZE","GRASS_KNOT"],"score":100},{"speciesId":"crawdaunt","speciesName":"Crawdaunt","rating":500,"matchups":[],"counters":[],"moves":{"fastMoves":[{"moveId":"SNARL","uses":10403},{"moveId":"WATERFALL","uses":8297}],"chargedMoves":[{"moveId":"NIGHT_SLASH","uses":8843},{"moveId":"CRABHAMMER","uses":6193},{"moveId":"BUBBLE_BEAM","uses":1864},{"moveId":"VICE_GRIP","uses":1807}]},"moveset":["SNARL","BUBBLE_BEAM","CRABHAMMER"],"score":100},{"speciesId":"crobat","speciesName":"Crobat","rating":500,"matchups":[],"counters":[],"moves":{"fastMoves":[{"moveId":"AIR_SLASH","uses":11319},{"moveId":"BITE","uses":7381}],"chargedMoves":[{"moveId":"SHADOW_BALL","uses":6374},{"moveId":"SLUDGE_BOMB","uses":6091},{"moveId":"AIR_CUTTER","uses":3210},{"moveId":"RETURN","uses":3027}]},"moveset":["AIR_SLASH","AIR_CUTTER","RETURN"],"score":100},{"speciesId":"crustle","speciesName":"Crustle","rating":500,"matchups":[],"counters":[],"moves":{"fastMoves":[{"moveId":"FURY_CUTTER","uses":9993},{"moveId":"SMACK_DOWN","uses":8707}],"chargedMoves":[{"moveId":"ROCK_SLIDE","uses":7172},{"moveId":"X_SCISSOR","uses":6366},{"moveId":"ROCK_BLAST","uses":5150}]},"moveset":["FURY_CUTTER","ROCK_BLAST","ROCK_SLIDE"],"score":100},{"speciesId":"cryogonal","speciesName":"Cryogonal","rating":500,"matchups":[],"counters":[],"moves":{"fastMoves":[{"moveId":"ICE_SHARD","uses":10842},{"moveId":"FROST_BREATH","uses":7858}],"chargedMoves":[{"moveId":"NIGHT_SLASH","uses":9343},{"moveId":"AURORA_BEAM","uses":4147},{"moveId":"SOLAR_BEAM","uses":2910},{"moveId":"WATER_PULSE","uses":2295}]},"moveset":["FROST_BREATH","AURORA_BEAM","NIGHT_SLASH"],"score":100},{"speciesId":"darmanitan_standard","speciesName":"Darmanitan (Standard)","rating":500,"matchups":[],"counters":[],"moves":{"fastMoves":[{"moveId":"INCINERATE","uses":12508},{"moveId":"FIRE_FANG","uses":4822},{"moveId":"TACKLE","uses":1378}],"chargedMoves":[{"moveId":"ROCK_SLIDE","uses":6747},{"moveId":"OVERHEAT","uses":5255},{"moveId":"PSYCHIC","uses":3585},{"moveId":"FOCUS_BLAST","uses":3109}]},"moveset":["FIRE_FANG","FOCUS_BLAST","OVERHEAT"],"score":100},{"speciesId":"delphox","speciesName":"Delphox","rating":500,"matchups":[],"counters":[],"moves":{"fastMoves":[{"moveId":"FIRE_SPIN","uses":11271},{"moveId":"SCRATCH","uses":4540},{"moveId":"ZEN_HEADBUTT","uses":2891}],"chargedMoves":[{"moveId":"FLAME_CHARGE","uses":7348},{"moveId":"PSYCHIC","uses":6641},{"moveId":"FLAMETHROWER","uses":3099},{"moveId":"FIRE_BLAST","uses":1652}]},"moveset":["FIRE_SPIN","FIRE_BLAST","FLAMETHROWER"],"score":100},{"speciesId":"dewgong","speciesName":"Dewgong","rating":500,"matchups":[],"counters":[],"moves":{"fastMoves":[{"moveId":"ICE_SHARD","uses":9391},{"moveId":"FROST_BREATH","uses":6989},{"moveId":"IRON_TAIL","uses":2316}],"chargedMoves":[{"moveId":"ICY_WIND","uses":8197},{"moveId":"AQUA_JET","uses":3909},{"moveId":"BLIZZARD","uses":3635},{"moveId":"WATER_PULSE","uses":1465},{"moveId":"AURORA_BEAM","uses":1461}]},"moveset":["FROST_BREATH","AQUA_JET","AURORA_BEAM"],"score":100},{"speciesId":"donphan","speciesName":"Donphan","rating":500,"matchups":[],"counters":[],"moves":{"fastMoves":[{"moveId":"COUNTER","uses":7790},{"moveId":"MUD_SLAP","uses":5464},{"moveId":"CHARM","uses":3782},{"moveId":"TACKLE","uses":1676}],"chargedMoves":[{"moveId":"EARTHQUAKE","uses":9183},{"moveId":"HEAVY_SLAM","uses":5121},{"moveId":"PLAY_ROUGH","uses":4378}]},"moveset":["CHARM","EARTHQUAKE","HEAVY_SLAM"],"score":100},{"speciesId":"dragonite","speciesName":"Dragonite","rating":500,"matchups":[],"counters":[],"moves":{"fastMoves":[{"moveId":"DRAGON_BREATH","uses":8560},{"moveId":"DRAGON_TAIL","uses":6806},{"moveId":"STEEL_WING","uses":3342}],"chargedMoves":[{"moveId":"DRAGON_CLAW","uses":7520},{"moveId":"HURRICANE","uses":3711},{"moveId":"OUTRAGE","uses":2050},{"moveId":"RETURN","uses":1970},{"moveId":"DRAGON_PULSE","uses":1430},{"moveId":"DRACO_METEOR","uses":1256},{"moveId":"HYPER_BEAM","uses":802}]},"moveset":["DRAGON_BREATH","DRACO_METEOR","DRAGON_CLAW"],"score":100},{"speciesId":"drapion","speciesName":"Drapion","rating":500,"matchups":[],"counters":[],"moves":{"fastMoves":[{"moveId":"INFESTATION","uses":5335},{"moveId":"POISON_STING","uses":4960},{"moveId":"ICE_FANG","uses":4216},{"moveId":"BITE","uses":4188}],"chargedMoves":[{"moveId":"AQUA_TAIL","uses":6568},{"moveId":"CRUNCH","uses":6146},{"moveId":"SLUDGE_BOMB","uses":4478},{"moveId":"FELL_STINGER","uses":1500}]},"moveset":["BITE","AQUA_TAIL","CRUNCH"],"score":100},{"speciesId":"drifblim","speciesName":"Drifblim","rating":500,"matchups":[],"counters":[],"moves":{"fastMoves":[{"moveId":"HEX","uses":13627},{"moveId":"ASTONISH","uses":5073}],"chargedMoves":[{"moveId":"SHADOW_BALL","uses":7285},{"moveId":"ICY_WIND","uses":7187},{"moveId":"OMINOUS_WIND","uses":4232}]},"moveset":["ASTONISH","ICY_WIND","OMINOUS_WIND"],"score":100},{"speciesId":"durant","speciesName":"Durant","rating":500,"matchups":[],"counters":[],"moves":{"fastMoves":[{"moveId":"BUG_BITE","uses":10736},{"moveId":"METAL_CLAW","uses":7964}],"chargedMoves":[{"moveId":"X_SCISSOR","uses":7939},{"moveId":"STONE_EDGE","uses":6250},{"moveId":"IRON_HEAD","uses":4515}]},"moveset":["BUG_BITE","IRON_HEAD","STONE_EDGE"],"score":100},{"speciesId":"electabuzz","speciesName":"Electabuzz","rating":500,"matchups":[],"counters":[],"moves":{"fastMoves":[{"moveId":"THUNDER_SHOCK","uses":14707},{"moveId":"LOW_KICK","uses":3993}],"chargedMoves":[{"moveId":"THUNDER_PUNCH","uses":8691},{"moveId":"RETURN","uses":3995},{"moveId":"THUNDERBOLT","uses":3231},{"moveId":"THUNDER","uses":2798}]},"moveset":["LOW_KICK","RETURN","THUNDER"],"score":100},{"speciesId":"electivire","speciesName":"Electivire","rating":500,"matchups":[],"counters":[],"moves":{"fastMoves":[{"moveId":"THUNDER_SHOCK","uses":16259},{"moveId":"LOW_KICK","uses":2441}],"chargedMoves":[{"moveId":"WILD_CHARGE","uses":6899},{"moveId":"ICE_PUNCH","uses":3450},{"moveId":"THUNDER_PUNCH","uses":3366},{"moveId":"FLAMETHROWER","uses":2633},{"moveId":"RETURN","uses":1261},{"moveId":"THUNDER","uses":1104}]},"moveset":["LOW_KICK","FLAMETHROWER","ICE_PUNCH"],"score":100},{"speciesId":"electrode","speciesName":"Electrode","rating":500,"matchups":[],"counters":[],"moves":{"fastMoves":[{"moveId":"VOLT_SWITCH","uses":9462},{"moveId":"SPARK","uses":6983},{"moveId":"TACKLE","uses":2261}],"chargedMoves":[{"moveId":"DISCHARGE","uses":6845},{"moveId":"FOUL_PLAY","uses":6536},{"moveId":"THUNDERBOLT","uses":2932},{"moveId":"HYPER_BEAM","uses":2390}]},"moveset":["SPARK","DISCHARGE","FOUL_PLAY"],"score":100},{"speciesId":"emboar","speciesName":"Emboar","rating":500,"matchups":[],"counters":[],"moves":{"fastMoves":[{"moveId":"EMBER","uses":14233},{"moveId":"LOW_KICK","uses":4467}],"chargedMoves":[{"moveId":"ROCK_SLIDE","uses":6956},{"moveId":"FLAME_CHARGE","uses":6535},{"moveId":"FOCUS_BLAST","uses":4314},{"moveId":"HEAT_WAVE","uses":891}]},"moveset":["EMBER","FLAME_CHARGE","FOCUS_BLAST"],"score":100},{"speciesId":"empoleon","speciesName":"Empoleon","rating":500,"matchups":[],"counters":[],"moves":{"fastMoves":[{"moveId":"WATERFALL","uses":11151},{"moveId":"METAL_CLAW","uses":7549}],"chargedMoves":[{"moveId":"HYDRO_CANNON","uses":9327},{"moveId":"DRILL_PECK","uses":4926},{"moveId":"BLIZZARD","uses":1834},{"moveId":"FLASH_CANNON","uses":1611},{"moveId":"HYDRO_PUMP","uses":994}]},"moveset":["METAL_CLAW","BLIZZARD","DRILL_PECK"],"score":100},{"speciesId":"escavalier","speciesName":"Escavalier","rating":500,"matchups":[],"counters":[],"moves":{"fastMoves":[{"moveId":"COUNTER","uses":11372},{"moveId":"BUG_BITE","uses":7328}],"chargedMoves":[{"moveId":"DRILL_RUN","uses":8096},{"moveId":"MEGAHORN","uses":6073},{"moveId":"AERIAL_ACE","uses":3928},{"moveId":"ACID_SPRAY","uses":617}]},"moveset":["BUG_BITE","ACID_SPRAY","AERIAL_ACE"],"score":100},{"speciesId":"espeon","speciesName":"Espeon","rating":500,"matchups":[],"counters":[],"moves":{"fastMoves":[{"moveId":"CONFUSION","uses":15216},{"moveId":"ZEN_HEADBUTT","uses":3485}],"chargedMoves":[{"moveId":"PSYCHIC","uses":8129},{"moveId":"LAST_RESORT","uses":5445},{"moveId":"FUTURE_SIGHT","uses":3537},{"moveId":"PSYBEAM","uses":1678}]},"moveset":["CONFUSION","FUTURE_SIGHT","LAST_RESORT"],"score":100},{"speciesId":"excadrill","speciesName":"Excadrill","rating":500,"matchups":[],"counters":[],"moves":{"fastMoves":[{"moveId":"MUD_SHOT","uses":9380},{"moveId":"MUD_SLAP","uses":5148},{"moveId":"METAL_CLAW","uses":4179}],"chargedMoves":[{"moveId":"DRILL_RUN","uses":7829},{"moveId":"ROCK_SLIDE","uses":5563},{"moveId":"IRON_HEAD","uses":3283},{"moveId":"EARTHQUAKE","uses":2004}]},"moveset":["METAL_CLAW","DRILL_RUN","EARTHQUAKE"],"score":100},{"speciesId":"exeggutor","speciesName":"Exeggutor","rating":500,"matchups":[],"counters":[],"moves":{"fastMoves":[{"moveId":"BULLET_SEED","uses":6703},{"moveId":"CONFUSION","uses":6018},{"moveId":"EXTRASENSORY","uses":4696},{"moveId":"ZEN_HEADBUTT","uses":1291}],"chargedMoves":[{"moveId":"SEED_BOMB","uses":6718},{"moveId":"PSYCHIC","uses":6018},{"moveId":"SOLAR_BEAM","uses":3078},{"moveId":"RETURN","uses":2864}]},"moveset":["BULLET_SEED","PSYCHIC","RETURN"],"score":100},{"speciesId":"feraligatr","speciesName":"Feraligatr","rating":500,"matchups":[],"counters":[],"moves":{"fastMoves":[{"moveId":"WATER_GUN","uses":6018},{"moveId":"WATERFALL","uses":5764},{"moveId":"ICE_FANG","uses":4205},{"moveId":"BITE","uses":2727}],"chargedMoves":[{"moveId":"HYDRO_CANNON","uses":10394},{"moveId":"CRUNCH","uses":3938},{"moveId":"ICE_BEAM","uses":3250},{"moveId":"HYDRO_PUMP","uses":1090}]},"moveset":["BITE","CRUNCH","HYDRO_CANNON"],"score":100},{"speciesId":"ferrothorn","speciesName":"Ferrothorn","rating":500,"matchups":[],"counters":[],"moves":{"fastMoves":[{"moveId":"BULLET_SEED","uses":11548},{"moveId":"METAL_CLAW","uses":7152}],"chargedMoves":[{"moveId":"POWER_WHIP","uses":6826},{"moveId":"MIRROR_SHOT","uses":4994},{"moveId":"THUNDER","uses":3653},{"moveId":"FLASH_CANNON","uses":2604},{"moveId":"ACID_SPRAY","uses":645}]},"moveset":["BULLET_SEED","ACID_SPRAY","FLASH_CANNON"],"score":100},{"speciesId":"floatzel","speciesName":"Floatzel","rating":500,"matchups":[],"counters":[],"moves":{"fastMoves":[{"moveId":"WATERFALL","uses":9550},{"moveId":"WATER_GUN","uses":9150}],"chargedMoves":[{"moveId":"HYDRO_PUMP","uses":7620},{"moveId":"AQUA_JET","uses":7128},{"moveId":"SWIFT","uses":3963}]},"moveset":["WATERFALL","AQUA_JET","HYDRO_PUMP"],"score":100},{"speciesId":"flygon","speciesName":"Flygon","rating":500,"matchups":[],"counters":[],"moves":{"fastMoves":[{"moveId":"MUD_SHOT","uses":10860},{"moveId":"DRAGON_TAIL","uses":7840}],"chargedMoves":[{"moveId":"DRAGON_CLAW","uses":6215},{"moveId":"EARTH_POWER","uses":4712},{"moveId":"STONE_EDGE","uses":4094},{"moveId":"EARTHQUAKE","uses":2027},{"moveId":"RETURN","uses":1642}]},"moveset":["DRAGON_TAIL","DRAGON_CLAW","EARTHQUAKE"],"score":100},{"speciesId":"forretress","speciesName":"Forretress","rating":500,"matchups":[],"counters":[],"moves":{"fastMoves":[{"moveId":"BUG_BITE","uses":11545},{"moveId":"STRUGGLE_BUG","uses":7155}],"chargedMoves":[{"moveId":"MIRROR_SHOT","uses":4548},{"moveId":"EARTHQUAKE","uses":4053},{"moveId":"HEAVY_SLAM","uses":3715},{"moveId":"RETURN","uses":2331},{"moveId":"ROCK_TOMB","uses":2061},{"moveId":"SAND_TOMB","uses":1998}]},"moveset":["BUG_BITE","EARTHQUAKE","HEAVY_SLAM"],"score":100},{"speciesId":"froslass","speciesName":"Froslass","rating":500,"matchups":[],"counters":[],"moves":{"fastMoves":[{"moveId":"POWDER_SNOW","uses":10432},{"moveId":"HEX","uses":8268}],"chargedMoves":[{"moveId":"AVALANCHE","uses":9245},{"moveId":"SHADOW_BALL","uses":5334},{"moveId":"CRUNCH","uses":4122}]},"moveset":["HEX","AVALANCHE","CRUNCH"],"score":100},{"speciesId":"gallade","speciesName":"Gallade","rating":500,"matchups":[],"counters":[],"moves":{"fastMoves":[{"moveId":"CONFUSION","uses":11341},{"moveId":"CHARM","uses":4547},{"moveId":"LOW_KICK","uses":2812}],"chargedMoves":[{"moveId":"CLOSE_COMBAT","uses":7090},{"moveId":"LEAF_BLADE","uses":5863},{"moveId":"SYNCHRONOISE","uses":3076},{"moveId":"PSYCHIC","uses":1397},{"moveId":"RETURN","uses":1256}]},"moveset":["CHARM","CLOSE_COMBAT","LEAF_BLADE"],"score":100},{"speciesId":"garbodor","speciesName":"Garbodor","rating":500,"matchups":[],"counters":[],"moves":{"fastMoves":[{"moveId":"INFESTATION","uses":15434},{"moveId":"TAKE_DOWN","uses":3266}],"chargedMoves":[{"moveId":"BODY_SLAM","uses":9096},{"moveId":"SEED_BOMB","uses":5748},{"moveId":"GUNK_SHOT","uses":3011},{"moveId":"ACID_SPRAY","uses":850}]},"moveset":["INFESTATION","ACID_SPRAY","BODY_SLAM"],"score":100},{"speciesId":"gardevoir","speciesName":"Gardevoir","rating":500,"matchups":[],"counters":[],"moves":{"fastMoves":[{"moveId":"CONFUSION","uses":7981},{"moveId":"CHARM","uses":6173},{"moveId":"CHARGE_BEAM","uses":4536}],"chargedMoves":[{"moveId":"SYNCHRONOISE","uses":5626},{"moveId":"SHADOW_BALL","uses":5025},{"moveId":"DAZZLING_GLEAM","uses":3067},{"moveId":"PSYCHIC","uses":2540},{"moveId":"RETURN","uses":2449}]},"moveset":["CHARGE_BEAM","DAZZLING_GLEAM","PSYCHIC"],"score":100},{"speciesId":"gengar","speciesName":"Gengar","rating":500,"matchups":[],"counters":[],"moves":{"fastMoves":[{"moveId":"SHADOW_CLAW","uses":7012},{"moveId":"HEX","uses":4565},{"moveId":"LICK","uses":3643},{"moveId":"SUCKER_PUNCH","uses":3483}],"chargedMoves":[{"moveId":"SHADOW_BALL","uses":3795},{"moveId":"SHADOW_PUNCH","uses":3743},{"moveId":"SLUDGE_BOMB","uses":3098},{"moveId":"DARK_PULSE","uses":2581},{"moveId":"PSYCHIC","uses":2260},{"moveId":"FOCUS_BLAST","uses":2182},{"moveId":"SLUDGE_WAVE","uses":1043}]},"moveset":["HEX","DARK_PULSE","FOCUS_BLAST"],"score":100},{"speciesId":"gigalith","speciesName":"Gigalith","rating":500,"matchups":[],"counters":[],"moves":{"fastMoves":[{"moveId":"SMACK_DOWN","uses":10984},{"moveId":"MUD_SLAP","uses":7716}],"chargedMoves":[{"moveId":"ROCK_SLIDE","uses":7905},{"moveId":"SUPER_POWER","uses":6430},{"moveId":"HEAVY_SLAM","uses":2358},{"moveId":"SOLAR_BEAM","uses":2017}]},"moveset":["MUD_SLAP","HEAVY_SLAM","ROCK_SLIDE"],"score":100},{"speciesId":"glaceon","speciesName":"Glaceon","rating":500,"matchups":[],"counters":[],"moves":{"fastMoves":[{"moveId":"ICE_SHARD","uses":11546},{"moveId":"FROST_BREATH","uses":7154}],"chargedMoves":[{"moveId":"AVALANCHE","uses":9910},{"moveId":"ICY_WIND","uses":3477},{"moveId":"LAST_RESORT","uses":3119},{"moveId":"ICE_BEAM","uses":2211}]},"moveset":["FROST_BREATH","AVALANCHE","ICE_BEAM"],"score":100},{"speciesId":"glalie","speciesName":"Glalie","rating":500,"matchups":[],"counters":[],"moves":{"fastMoves":[{"moveId":"ICE_SHARD","uses":11293},{"moveId":"FROST_BREATH","uses":7407}],"chargedMoves":[{"moveId":"AVALANCHE","uses":11499},{"moveId":"SHADOW_BALL","uses":5253},{"moveId":"GYRO_BALL","uses":1941}]},"moveset":["FROST_BREATH","AVALANCHE","GYRO_BALL"],"score":100},{"speciesId":"gliscor","speciesName":"Gliscor","rating":500,"matchups":[],"counters":[],"moves":{"fastMoves":[{"moveId":"FURY_CUTTER","uses":9465},{"moveId":"WING_ATTACK","uses":9235}],"chargedMoves":[{"moveId":"NIGHT_SLASH","uses":6181},{"moveId":"EARTHQUAKE","uses":4458},{"moveId":"AERIAL_ACE","uses":4032},{"moveId":"SAND_TOMB","uses":2172},{"moveId":"RETURN","uses":1862}]},"moveset":["FURY_CUTTER","AERIAL_ACE","EARTHQUAKE"],"score":100},{"speciesId":"golem","speciesName":"Golem","rating":500,"matchups":[],"counters":[],"moves":{"fastMoves":[{"moveId":"MUD_SHOT","uses":8125},{"moveId":"ROCK_THROW","uses":5628},{"moveId":"MUD_SLAP","uses":4953}],"chargedMoves":[{"moveId":"STONE_EDGE","uses":5952},{"moveId":"EARTHQUAKE","uses":5619},{"moveId":"ROCK_BLAST","uses":5385},{"moveId":"ANCIENT_POWER","uses":1735}]},"moveset":["MUD_SHOT","ANCIENT_POWER","EARTHQUAKE"],"score":100},{"speciesId":"golem_alolan","speciesName":"Golem (Alolan)","rating":500,"matchups":[],"counters":[],"moves":{"fastMoves":[{"moveId":"VOLT_SWITCH","uses":12088},{"moveId":"ROCK_THROW","uses":6612}],"chargedMoves":[{"moveId":"WILD_CHARGE","uses":8971},{"moveId":"STONE_EDGE","uses":5098},{"moveId":"ROCK_BLAST","uses":4639}]},"moveset":["ROCK_THROW","ROCK_BLAST","STONE_EDGE"],"score":100},{"speciesId":"golurk","speciesName":"Golurk","rating":500,"matchups":[],"counters":[],"moves":{"fastMoves":[{"moveId":"MUD_SLAP","uses":12684},{"moveId":"ASTONISH","uses":6016}],"chargedMoves":[{"moveId":"SHADOW_PUNCH","uses":6889},{"moveId":"EARTH_POWER","uses":6005},{"moveId":"DYNAMIC_PUNCH","uses":5816}]},"moveset":["ASTONISH","DYNAMIC_PUNCH","EARTH_POWER"],"score":100},{"speciesId":"gothitelle","speciesName":"Gothitelle","rating":500,"matchups":[],"counters":[],"moves":{"fastMoves":[{"moveId":"CONFUSION","uses":11676},{"moveId":"CHARM","uses":7024}],"chargedMoves":[{"moveId":"ROCK_SLIDE","uses":9257},{"moveId":"PSYCHIC","uses":6598},{"moveId":"FUTURE_SIGHT","uses":2874}]},"moveset":["CHARM","FUTURE_SIGHT","PSYCHIC"],"score":100},{"speciesId":"granbull","speciesName":"Granbull","rating":500,"matchups":[],"counters":[],"moves":{"fastMoves":[{"moveId":"SNARL","uses":9201},{"moveId":"CHARM","uses":5971},{"moveId":"BITE","uses":3531}],"chargedMoves":[{"moveId":"CLOSE_COMBAT","uses":9681},{"moveId":"CRUNCH","uses":5542},{"moveId":"PLAY_ROUGH","uses":3494}]},"moveset":["BITE","CLOSE_COMBAT","CRUNCH"],"score":100},{"speciesId":"greninja","speciesName":"Greninja","rating":500,"matchups":[],"counters":[],"moves":{"fastMoves":[{"moveId":"BUBBLE","uses":10231},{"moveId":"FEINT_ATTACK","uses":8469}],"chargedMoves":[{"moveId":"NIGHT_SLASH","uses":7913},{"moveId":"SURF","uses":7012},{"moveId":"AERIAL_ACE","uses":2632},{"moveId":"HYDRO_PUMP","uses":1132}]},"moveset":["BUBBLE","AERIAL_ACE","HYDRO_PUMP"],"score":100},{"speciesId":"gyarados","speciesName":"Gyarados","rating":500,"matchups":[],"counters":[],"moves":{"fastMoves":[{"moveId":"WATERFALL","uses":5786},{"moveId":"DRAGON_BREATH","uses":5597},{"moveId":"DRAGON_TAIL","uses":4499},{"moveId":"BITE","uses":2822}],"chargedMoves":[{"moveId":"AQUA_TAIL","uses":7295},{"moveId":"CRUNCH","uses":3749},{"moveId":"OUTRAGE","uses":2527},{"moveId":"RETURN","uses":1780},{"moveId":"TWISTER","uses":1380},{"moveId":"HYDRO_PUMP","uses":1160},{"moveId":"DRAGON_PULSE","uses":868}]},"moveset":["BITE","AQUA_TAIL","CRUNCH"],"score":100},{"speciesId":"hariyama","speciesName":"Hariyama","rating":500,"matchups":[],"counters":[],"moves":{"fastMoves":[{"moveId":"COUNTER","uses":11850},{"moveId":"BULLET_PUNCH","uses":6850}],"chargedMoves":[{"moveId":"CLOSE_COMBAT","uses":8107},{"moveId":"SUPER_POWER","uses":5989},{"moveId":"HEAVY_SLAM","uses":2440},{"moveId":"DYNAMIC_PUNCH","uses":2173}]},"moveset":["BULLET_PUNCH","CLOSE_COMBAT","DYNAMIC_PUNCH"],"score":100},{"speciesId":"heatmor","speciesName":"Heatmor","rating":500,"matchups":[],"counters":[],"moves":{"fastMoves":[{"moveId":"FIRE_SPIN","uses":10726},{"moveId":"LICK","uses":7974}],"chargedMoves":[{"moveId":"FLAMETHROWER","uses":8233},{"moveId":"THUNDER_PUNCH","uses":7336},{"moveId":"POWER_UP_PUNCH","uses":3140}]},"moveset":["FIRE_SPIN","FLAMETHROWER","POWER_UP_PUNCH"],"score":100},{"speciesId":"hippowdon","speciesName":"Hippowdon","rating":500,"matchups":[],"counters":[],"moves":{"fastMoves":[{"moveId":"THUNDER_FANG","uses":5155},{"moveId":"FIRE_FANG","uses":5097},{"moveId":"ICE_FANG","uses":5074},{"moveId":"BITE","uses":3359}],"chargedMoves":[{"moveId":"BODY_SLAM","uses":6411},{"moveId":"EARTH_POWER","uses":5350},{"moveId":"STONE_EDGE","uses":4652},{"moveId":"EARTHQUAKE","uses":2320}]},"moveset":["BITE","BODY_SLAM","EARTHQUAKE"],"score":100},{"speciesId":"hitmonchan","speciesName":"Hitmonchan","rating":500,"matchups":[],"counters":[],"moves":{"fastMoves":[{"moveId":"COUNTER","uses":10467},{"moveId":"BULLET_PUNCH","uses":6140},{"moveId":"ROCK_SMASH","uses":2079}],"chargedMoves":[{"moveId":"CLOSE_COMBAT","uses":6181},{"moveId":"ICE_PUNCH","uses":2859},{"moveId":"BRICK_BREAK","uses":2740},{"moveId":"FIRE_PUNCH","uses":2674},{"moveId":"THUNDER_PUNCH","uses":2633},{"moveId":"RETURN","uses":1101},{"moveId":"POWER_UP_PUNCH","uses":541}]},"moveset":["BULLET_PUNCH","BRICK_BREAK","CLOSE_COMBAT"],"score":100},{"speciesId":"hitmontop","speciesName":"Hitmontop","rating":500,"matchups":[],"counters":[],"moves":{"fastMoves":[{"moveId":"COUNTER","uses":15519},{"moveId":"ROCK_SMASH","uses":3181}],"chargedMoves":[{"moveId":"CLOSE_COMBAT","uses":11682},{"moveId":"STONE_EDGE","uses":5308},{"moveId":"GYRO_BALL","uses":1724}]},"moveset":["COUNTER","CLOSE_COMBAT","GYRO_BALL"],"score":100},{"speciesId":"honchkrow","speciesName":"Honchkrow","rating":500,"matchups":[],"counters":[],"moves":{"fastMoves":[{"moveId":"SNARL","uses":13886},{"moveId":"PECK","uses":4814}],"chargedMoves":[{"moveId":"BRAVE_BIRD","uses":6798},{"moveId":"SKY_ATTACK","uses":5044},{"moveId":"DARK_PULSE","uses":4523},{"moveId":"PSYCHIC","uses":2312}]},"moveset":["PECK","BRAVE_BIRD","DARK_PULSE"],"score":100},{"speciesId":"houndoom","speciesName":"Houndoom","rating":500,"matchups":[],"counters":[],"moves":{"fastMoves":[{"moveId":"SNARL","uses":10918},{"moveId":"FIRE_FANG","uses":7782}],"chargedMoves":[{"moveId":"CRUNCH","uses":6562},{"moveId":"FLAMETHROWER","uses":5166},{"moveId":"FOUL_PLAY","uses":3309},{"moveId":"RETURN","uses":2266},{"moveId":"FIRE_BLAST","uses":1388}]},"moveset":["FIRE_FANG","CRUNCH","FIRE_BLAST"],"score":100},{"speciesId":"huntail","speciesName":"Huntail","rating":500,"matchups":[],"counters":[],"moves":{"fastMoves":[{"moveId":"WATER_GUN","uses":12364},{"moveId":"BITE","uses":6336}],"chargedMoves":[{"moveId":"AQUA_TAIL","uses":9570},{"moveId":"CRUNCH","uses":5055},{"moveId":"ICE_BEAM","uses":4094}]},"moveset":["BITE","AQUA_TAIL","CRUNCH"],"score":100},{"speciesId":"hypno","speciesName":"Hypno","rating":500,"matchups":[],"counters":[],"moves":{"fastMoves":[{"moveId":"CONFUSION","uses":15894},{"moveId":"ZEN_HEADBUTT","uses":2806}],"chargedMoves":[{"moveId":"PSYSHOCK","uses":3052},{"moveId":"FIRE_PUNCH","uses":2837},{"moveId":"ICE_PUNCH","uses":2745},{"moveId":"THUNDER_PUNCH","uses":2734},{"moveId":"SHADOW_BALL","uses":2332},{"moveId":"FOCUS_BLAST","uses":1664},{"moveId":"PSYCHIC","uses":1186},{"moveId":"RETURN","uses":1093},{"moveId":"FUTURE_SIGHT","uses":1028}]},"moveset":["CONFUSION","FIRE_PUNCH","FOCUS_BLAST"],"score":100},{"speciesId":"infernape","speciesName":"Infernape","rating":500,"matchups":[],"counters":[],"moves":{"fastMoves":[{"moveId":"FIRE_SPIN","uses":14209},{"moveId":"ROCK_SMASH","uses":4491}],"chargedMoves":[{"moveId":"CLOSE_COMBAT","uses":8386},{"moveId":"BLAST_BURN","uses":7093},{"moveId":"FLAMETHROWER","uses":1635},{"moveId":"SOLAR_BEAM","uses":1563}]},"moveset":["FIRE_SPIN","BLAST_BURN","CLOSE_COMBAT"],"score":100},{"speciesId":"jolteon","speciesName":"Jolteon","rating":500,"matchups":[],"counters":[],"moves":{"fastMoves":[{"moveId":"VOLT_SWITCH","uses":10507},{"moveId":"THUNDER_SHOCK","uses":8193}],"chargedMoves":[{"moveId":"DISCHARGE","uses":7674},{"moveId":"LAST_RESORT","uses":4895},{"moveId":"THUNDERBOLT","uses":3301},{"moveId":"THUNDER","uses":2849}]},"moveset":["THUNDER_SHOCK","DISCHARGE","LAST_RESORT"],"score":100},{"speciesId":"kabutops","speciesName":"Kabutops","rating":500,"matchups":[],"counters":[],"moves":{"fastMoves":[{"moveId":"MUD_SHOT","uses":6107},{"moveId":"FURY_CUTTER","uses":5638},{"moveId":"WATERFALL","uses":5058},{"moveId":"ROCK_SMASH","uses":1911}],"chargedMoves":[{"moveId":"STONE_EDGE","uses":9432},{"moveId":"ANCIENT_POWER","uses":5455},{"moveId":"WATER_PULSE","uses":3814}]},"moveset":["FURY_CUTTER","ANCIENT_POWER","STONE_EDGE"],"score":100},{"speciesId":"kangaskhan","speciesName":"Kangaskhan","rating":500,"matchups":[],"counters":[],"moves":{"fastMoves":[{"moveId":"MUD_SLAP","uses":13748},{"moveId":"LOW_KICK","uses":4952}],"chargedMoves":[{"moveId":"STOMP","uses":4436},{"moveId":"CRUNCH","uses":4032},{"moveId":"BRICK_BREAK","uses":3731},{"moveId":"EARTHQUAKE","uses":3104},{"moveId":"OUTRAGE","uses":2660},{"moveId":"POWER_UP_PUNCH","uses":755}]},"moveset":["LOW_KICK","BRICK_BREAK","CRUNCH"],"score":100},{"speciesId":"kingdra","speciesName":"Kingdra","rating":500,"matchups":[],"counters":[],"moves":{"fastMoves":[{"moveId":"DRAGON_BREATH","uses":7478},{"moveId":"WATERFALL","uses":5618},{"moveId":"WATER_GUN","uses":5602}],"chargedMoves":[{"moveId":"OUTRAGE","uses":6260},{"moveId":"OCTAZOOKA","uses":4784},{"moveId":"HYDRO_PUMP","uses":4022},{"moveId":"BLIZZARD","uses":3624}]},"moveset":["DRAGON_BREATH","BLIZZARD","HYDRO_PUMP"],"score":100},{"speciesId":"kingler","speciesName":"Kingler","rating":500,"matchups":[],"counters":[],"moves":{"fastMoves":[{"moveId":"MUD_SHOT","uses":7929},{"moveId":"BUBBLE","uses":7155},{"moveId":"METAL_CLAW","uses":3627}],"chargedMoves":[{"moveId":"CRABHAMMER","uses":8925},{"moveId":"X_SCISSOR","uses":6019},{"moveId":"VICE_GRIP","uses":2455},{"moveId":"WATER_PULSE","uses":1292}]},"moveset":["BUBBLE","CRABHAMMER","VICE_GRIP"],"score":100},{"speciesId":"klinklang","speciesName":"Klinklang","rating":500,"matchups":[],"counters":[],"moves":{"fastMoves":[{"moveId":"THUNDER_SHOCK","uses":11684},{"moveId":"CHARGE_BEAM","uses":7016}],"chargedMoves":[{"moveId":"MIRROR_SHOT","uses":7468},{"moveId":"ZAP_CANNON","uses":4182},{"moveId":"FLASH_CANNON","uses":3897},{"moveId":"HYPER_BEAM","uses":3153}]},"moveset":["CHARGE_BEAM","FLASH_CANNON","HYPER_BEAM"],"score":100},{"speciesId":"krookodile","speciesName":"Krookodile","rating":500,"matchups":[],"counters":[],"moves":{"fastMoves":[{"moveId":"SNARL","uses":10900},{"moveId":"MUD_SLAP","uses":7800}],"chargedMoves":[{"moveId":"CRUNCH","uses":8160},{"moveId":"EARTHQUAKE","uses":6457},{"moveId":"OUTRAGE","uses":4093}]},"moveset":["MUD_SLAP","CRUNCH","EARTHQUAKE"],"score":100},{"speciesId":"lairon","speciesName":"Lairon","rating":500,"matchups":[],"counters":[],"moves":{"fastMoves":[{"moveId":"METAL_CLAW","uses":13575},{"moveId":"IRON_TAIL","uses":5125}],"chargedMoves":[{"moveId":"ROCK_SLIDE","uses":7691},{"moveId":"BODY_SLAM","uses":6500},{"moveId":"HEAVY_SLAM","uses":3578},{"moveId":"RETURN","uses":943}]},"moveset":["IRON_TAIL","BODY_SLAM","HEAVY_SLAM"],"score":100},{"speciesId":"lanturn","speciesName":"Lanturn","rating":500,"matchups":[],"counters":[],"moves":{"fastMoves":[{"moveId":"WATER_GUN","uses":7194},{"moveId":"SPARK","uses":6965},{"moveId":"CHARGE_BEAM","uses":4536}],"chargedMoves":[{"moveId":"THUNDERBOLT","uses":8439},{"moveId":"HYDRO_PUMP","uses":6598},{"moveId":"THUNDER","uses":3679}]},"moveset":["CHARGE_BEAM","HYDRO_PUMP","THUNDER"],"score":100},{"speciesId":"leafeon","speciesName":"Leafeon","rating":500,"matchups":[],"counters":[],"moves":{"fastMoves":[{"moveId":"QUICK_ATTACK","uses":10120},{"moveId":"RAZOR_LEAF","uses":8580}],"chargedMoves":[{"moveId":"LEAF_BLADE","uses":12585},{"moveId":"LAST_RESORT","uses":3292},{"moveId":"ENERGY_BALL","uses":1770},{"moveId":"SOLAR_BEAM","uses":1044}]},"moveset":["QUICK_ATTACK","ENERGY_BALL","LAST_RESORT"],"score":100},{"speciesId":"leavanny","speciesName":"Leavanny","rating":500,"matchups":[],"counters":[],"moves":{"fastMoves":[{"moveId":"BUG_BITE","uses":10602},{"moveId":"RAZOR_LEAF","uses":8098}],"chargedMoves":[{"moveId":"LEAF_BLADE","uses":11823},{"moveId":"X_SCISSOR","uses":5581},{"moveId":"SILVER_WIND","uses":1266}]},"moveset":["BUG_BITE","LEAF_BLADE","SILVER_WIND"],"score":100},{"speciesId":"lucario","speciesName":"Lucario","rating":500,"matchups":[],"counters":[],"moves":{"fastMoves":[{"moveId":"COUNTER","uses":11177},{"moveId":"BULLET_PUNCH","uses":7523}],"chargedMoves":[{"moveId":"CLOSE_COMBAT","uses":9130},{"moveId":"SHADOW_BALL","uses":3905},{"moveId":"AURA_SPHERE","uses":2044},{"moveId":"FLASH_CANNON","uses":1998},{"moveId":"POWER_UP_PUNCH","uses":1621}]},"moveset":["BULLET_PUNCH","AURA_SPHERE","CLOSE_COMBAT"],"score":100},{"speciesId":"ludicolo","speciesName":"Ludicolo","rating":500,"matchups":[],"counters":[],"moves":{"fastMoves":[{"moveId":"BUBBLE","uses":11372},{"moveId":"RAZOR_LEAF","uses":7328}],"chargedMoves":[{"moveId":"ENERGY_BALL","uses":5847},{"moveId":"ICE_BEAM","uses":4963},{"moveId":"HYDRO_PUMP","uses":4457},{"moveId":"SOLAR_BEAM","uses":1721},{"moveId":"BLIZZARD","uses":1710}]},"moveset":["BUBBLE","BLIZZARD","ENERGY_BALL"],"score":100},{"speciesId":"lunatone","speciesName":"Lunatone","rating":500,"matchups":[],"counters":[],"moves":{"fastMoves":[{"moveId":"CONFUSION","uses":9745},{"moveId":"ROCK_THROW","uses":8955}],"chargedMoves":[{"moveId":"ROCK_SLIDE","uses":9486},{"moveId":"PSYCHIC","uses":5164},{"moveId":"MOONBLAST","uses":4041}]},"moveset":["CONFUSION","MOONBLAST","PSYCHIC"],"score":100},{"speciesId":"luxray","speciesName":"Luxray","rating":500,"matchups":[],"counters":[],"moves":{"fastMoves":[{"moveId":"SPARK","uses":2717},{"moveId":"SNARL","uses":2253},{"moveId":"HIDDEN_POWER_ELECTRIC","uses":1121},{"moveId":"HIDDEN_POWER_GROUND","uses":1014},{"moveId":"HIDDEN_POWER_ROCK","uses":959},{"moveId":"HIDDEN_POWER_FIRE","uses":933},{"moveId":"HIDDEN_POWER_FIGHTING","uses":921},{"moveId":"HIDDEN_POWER_WATER","uses":902},{"moveId":"HIDDEN_POWER_ICE","uses":888},{"moveId":"HIDDEN_POWER_FLYING","uses":848},{"moveId":"HIDDEN_POWER_DARK","uses":826},{"moveId":"HIDDEN_POWER_GHOST","uses":821},{"moveId":"HIDDEN_POWER_GRASS","uses":814},{"moveId":"HIDDEN_POWER_BUG","uses":765},{"moveId":"HIDDEN_POWER_PSYCHIC","uses":756},{"moveId":"HIDDEN_POWER_STEEL","uses":732},{"moveId":"HIDDEN_POWER_DRAGON","uses":731},{"moveId":"HIDDEN_POWER_POISON","uses":679}],"chargedMoves":[{"moveId":"WILD_CHARGE","uses":11694},{"moveId":"CRUNCH","uses":5149},{"moveId":"HYPER_BEAM","uses":1849}]},"moveset":["HIDDEN_POWER_BUG","CRUNCH","HYPER_BEAM"],"score":100},{"speciesId":"magmar","speciesName":"Magmar","rating":500,"matchups":[],"counters":[],"moves":{"fastMoves":[{"moveId":"KARATE_CHOP","uses":9591},{"moveId":"EMBER","uses":9109}],"chargedMoves":[{"moveId":"FIRE_PUNCH","uses":9412},{"moveId":"RETURN","uses":3904},{"moveId":"FLAMETHROWER","uses":3510},{"moveId":"FIRE_BLAST","uses":1904}]},"moveset":["EMBER","FIRE_BLAST","FIRE_PUNCH"],"score":100},{"speciesId":"magmortar","speciesName":"Magmortar","rating":500,"matchups":[],"counters":[],"moves":{"fastMoves":[{"moveId":"KARATE_CHOP","uses":9812},{"moveId":"FIRE_SPIN","uses":8888}],"chargedMoves":[{"moveId":"FIRE_PUNCH","uses":5707},{"moveId":"BRICK_BREAK","uses":3936},{"moveId":"THUNDERBOLT","uses":3261},{"moveId":"PSYCHIC","uses":2826},{"moveId":"RETURN","uses":1819},{"moveId":"FIRE_BLAST","uses":1150}]},"moveset":["FIRE_SPIN","BRICK_BREAK","FIRE_BLAST"],"score":100},{"speciesId":"magneton","speciesName":"Magneton","rating":500,"matchups":[],"counters":[],"moves":{"fastMoves":[{"moveId":"THUNDER_SHOCK","uses":7539},{"moveId":"SPARK","uses":6849},{"moveId":"CHARGE_BEAM","uses":4304}],"chargedMoves":[{"moveId":"MAGNET_BOMB","uses":6529},{"moveId":"DISCHARGE","uses":6359},{"moveId":"RETURN","uses":2628},{"moveId":"ZAP_CANNON","uses":1837},{"moveId":"FLASH_CANNON","uses":1369}]},"moveset":["CHARGE_BEAM","DISCHARGE","FLASH_CANNON"],"score":100},{"speciesId":"magnezone","speciesName":"Magnezone","rating":500,"matchups":[],"counters":[],"moves":{"fastMoves":[{"moveId":"SPARK","uses":11542},{"moveId":"CHARGE_BEAM","uses":7158}],"chargedMoves":[{"moveId":"WILD_CHARGE","uses":9707},{"moveId":"MIRROR_SHOT","uses":3944},{"moveId":"FLASH_CANNON","uses":2071},{"moveId":"RETURN","uses":1897},{"moveId":"ZAP_CANNON","uses":1102}]},"moveset":["CHARGE_BEAM","FLASH_CANNON","MIRROR_SHOT"],"score":100},{"speciesId":"mamoswine","speciesName":"Mamoswine","rating":500,"matchups":[],"counters":[],"moves":{"fastMoves":[{"moveId":"POWDER_SNOW","uses":11638},{"moveId":"MUD_SLAP","uses":7062}],"chargedMoves":[{"moveId":"AVALANCHE","uses":8065},{"moveId":"STONE_EDGE","uses":3740},{"moveId":"BULLDOZE","uses":3166},{"moveId":"ANCIENT_POWER","uses":2171},{"moveId":"RETURN","uses":1583}]},"moveset":["MUD_SLAP","ANCIENT_POWER","AVALANCHE"],"score":100},{"speciesId":"manectric","speciesName":"Manectric","rating":500,"matchups":[],"counters":[],"moves":{"fastMoves":[{"moveId":"SNARL","uses":11299},{"moveId":"CHARGE_BEAM","uses":7401}],"chargedMoves":[{"moveId":"WILD_CHARGE","uses":12935},{"moveId":"FLAME_BURST","uses":3722},{"moveId":"THUNDER","uses":2019}]},"moveset":["CHARGE_BEAM","FLAME_BURST","THUNDER"],"score":100},{"speciesId":"mantine","speciesName":"Mantine","rating":500,"matchups":[],"counters":[],"moves":{"fastMoves":[{"moveId":"WING_ATTACK","uses":6503},{"moveId":"BUBBLE","uses":6489},{"moveId":"BULLET_SEED","uses":5701}],"chargedMoves":[{"moveId":"AERIAL_ACE","uses":6432},{"moveId":"ICE_BEAM","uses":5154},{"moveId":"BUBBLE_BEAM","uses":3619},{"moveId":"WATER_PULSE","uses":3490}]},"moveset":["BUBBLE","AERIAL_ACE","BUBBLE_BEAM"],"score":100},{"speciesId":"maractus","speciesName":"Maractus","rating":500,"matchups":[],"counters":[],"moves":{"fastMoves":[{"moveId":"BULLET_SEED","uses":10243},{"moveId":"POISON_JAB","uses":8457}],"chargedMoves":[{"moveId":"AERIAL_ACE","uses":8041},{"moveId":"PETAL_BLIZZARD","uses":7607},{"moveId":"SOLAR_BEAM","uses":3081}]},"moveset":["BULLET_SEED","AERIAL_ACE","PETAL_BLIZZARD"],"score":100},{"speciesId":"masquerain","speciesName":"Masquerain","rating":500,"matchups":[],"counters":[],"moves":{"fastMoves":[{"moveId":"INFESTATION","uses":9627},{"moveId":"AIR_SLASH","uses":9073}],"chargedMoves":[{"moveId":"LUNGE","uses":7933},{"moveId":"OMINOUS_WIND","uses":3272},{"moveId":"AIR_CUTTER","uses":3094},{"moveId":"BUBBLE_BEAM","uses":2591},{"moveId":"SILVER_WIND","uses":1825}]},"moveset":["AIR_SLASH","AIR_CUTTER","BUBBLE_BEAM"],"score":100},{"speciesId":"meganium","speciesName":"Meganium","rating":500,"matchups":[],"counters":[],"moves":{"fastMoves":[{"moveId":"VINE_WHIP","uses":12971},{"moveId":"RAZOR_LEAF","uses":5729}],"chargedMoves":[{"moveId":"FRENZY_PLANT","uses":11344},{"moveId":"EARTHQUAKE","uses":4556},{"moveId":"PETAL_BLIZZARD","uses":1539},{"moveId":"SOLAR_BEAM","uses":1268}]},"moveset":["RAZOR_LEAF","EARTHQUAKE","FRENZY_PLANT"],"score":100},{"speciesId":"meowstic","speciesName":"Meowstic (Male)","rating":500,"matchups":[],"counters":[],"moves":{"fastMoves":[{"moveId":"CONFUSION","uses":10315},{"moveId":"SUCKER_PUNCH","uses":8385}],"chargedMoves":[{"moveId":"PSYCHIC","uses":7462},{"moveId":"THUNDERBOLT","uses":5726},{"moveId":"ENERGY_BALL","uses":5517}]},"moveset":["CONFUSION","ENERGY_BALL","PSYCHIC"],"score":100},{"speciesId":"metagross","speciesName":"Metagross","rating":500,"matchups":[],"counters":[],"moves":{"fastMoves":[{"moveId":"BULLET_PUNCH","uses":15778},{"moveId":"ZEN_HEADBUTT","uses":2922}],"chargedMoves":[{"moveId":"METEOR_MASH","uses":6949},{"moveId":"PSYCHIC","uses":4469},{"moveId":"EARTHQUAKE","uses":4030},{"moveId":"RETURN","uses":2164},{"moveId":"FLASH_CANNON","uses":1117}]},"moveset":["BULLET_PUNCH","EARTHQUAKE","FLASH_CANNON"],"score":100},{"speciesId":"milotic","speciesName":"Milotic","rating":500,"matchups":[],"counters":[],"moves":{"fastMoves":[{"moveId":"WATERFALL","uses":10039},{"moveId":"DRAGON_TAIL","uses":8661}],"chargedMoves":[{"moveId":"SURF","uses":12234},{"moveId":"BLIZZARD","uses":3873},{"moveId":"HYPER_BEAM","uses":2580}]},"moveset":["DRAGON_TAIL","BLIZZARD","HYPER_BEAM"],"score":100},{"speciesId":"mismagius","speciesName":"Mismagius","rating":500,"matchups":[],"counters":[],"moves":{"fastMoves":[{"moveId":"HEX","uses":10431},{"moveId":"SUCKER_PUNCH","uses":8269}],"chargedMoves":[{"moveId":"SHADOW_BALL","uses":7773},{"moveId":"DARK_PULSE","uses":5294},{"moveId":"RETURN","uses":3032},{"moveId":"DAZZLING_GLEAM","uses":2567}]},"moveset":["HEX","DARK_PULSE","DAZZLING_GLEAM"],"score":100},{"speciesId":"muk","speciesName":"Muk","rating":500,"matchups":[],"counters":[],"moves":{"fastMoves":[{"moveId":"POISON_JAB","uses":5938},{"moveId":"LICK","uses":4959},{"moveId":"INFESTATION","uses":4927},{"moveId":"ACID","uses":2877}],"chargedMoves":[{"moveId":"THUNDER_PUNCH","uses":5542},{"moveId":"DARK_PULSE","uses":5081},{"moveId":"SLUDGE_WAVE","uses":3429},{"moveId":"RETURN","uses":2537},{"moveId":"GUNK_SHOT","uses":1346},{"moveId":"ACID_SPRAY","uses":776}]},"moveset":["ACID","ACID_SPRAY","DARK_PULSE"],"score":100},{"speciesId":"muk_alolan","speciesName":"Muk (Alolan)","rating":500,"matchups":[],"counters":[],"moves":{"fastMoves":[{"moveId":"SNARL","uses":7171},{"moveId":"POISON_JAB","uses":6822},{"moveId":"BITE","uses":4724}],"chargedMoves":[{"moveId":"DARK_PULSE","uses":10421},{"moveId":"SLUDGE_WAVE","uses":5122},{"moveId":"GUNK_SHOT","uses":2017},{"moveId":"ACID_SPRAY","uses":1136}]},"moveset":["BITE","ACID_SPRAY","DARK_PULSE"],"score":100},{"speciesId":"munchlax","speciesName":"Munchlax","rating":500,"matchups":[],"counters":[],"moves":{"fastMoves":[{"moveId":"LICK","uses":12304},{"moveId":"TACKLE","uses":6396}],"chargedMoves":[{"moveId":"BODY_SLAM","uses":12830},{"moveId":"BULLDOZE","uses":3712},{"moveId":"GUNK_SHOT","uses":2163}]},"moveset":["LICK","BODY_SLAM","BULLDOZE"],"score":100},{"speciesId":"nidoking","speciesName":"Nidoking","rating":500,"matchups":[],"counters":[],"moves":{"fastMoves":[{"moveId":"FURY_CUTTER","uses":8658},{"moveId":"POISON_JAB","uses":8534},{"moveId":"IRON_TAIL","uses":1500}],"chargedMoves":[{"moveId":"EARTH_POWER","uses":6168},{"moveId":"MEGAHORN","uses":4005},{"moveId":"SLUDGE_WAVE","uses":3512},{"moveId":"EARTHQUAKE","uses":2641},{"moveId":"RETURN","uses":2343}]},"moveset":["FURY_CUTTER","EARTHQUAKE","EARTH_POWER"],"score":100},{"speciesId":"nidoqueen","speciesName":"Nidoqueen","rating":500,"matchups":[],"counters":[],"moves":{"fastMoves":[{"moveId":"POISON_JAB","uses":13227},{"moveId":"BITE","uses":5473}],"chargedMoves":[{"moveId":"EARTH_POWER","uses":5869},{"moveId":"STONE_EDGE","uses":5058},{"moveId":"SLUDGE_WAVE","uses":3191},{"moveId":"EARTHQUAKE","uses":2522},{"moveId":"RETURN","uses":2040}]},"moveset":["BITE","EARTHQUAKE","EARTH_POWER"],"score":100},{"speciesId":"ninetales","speciesName":"Ninetales","rating":500,"matchups":[],"counters":[],"moves":{"fastMoves":[{"moveId":"FIRE_SPIN","uses":7093},{"moveId":"EMBER","uses":6741},{"moveId":"FEINT_ATTACK","uses":4858}],"chargedMoves":[{"moveId":"WEATHER_BALL_FIRE","uses":7499},{"moveId":"PSYSHOCK","uses":2796},{"moveId":"OVERHEAT","uses":2537},{"moveId":"SOLAR_BEAM","uses":1882},{"moveId":"RETURN","uses":1424},{"moveId":"FLAMETHROWER","uses":1385},{"moveId":"FIRE_BLAST","uses":736},{"moveId":"HEAT_WAVE","uses":438}]},"moveset":["EMBER","FIRE_BLAST","FLAMETHROWER"],"score":100},{"speciesId":"noctowl","speciesName":"Noctowl","rating":500,"matchups":[],"counters":[],"moves":{"fastMoves":[{"moveId":"WING_ATTACK","uses":10990},{"moveId":"EXTRASENSORY","uses":7710}],"chargedMoves":[{"moveId":"SKY_ATTACK","uses":11116},{"moveId":"PSYCHIC","uses":4892},{"moveId":"NIGHT_SHADE","uses":2685}]},"moveset":["EXTRASENSORY","NIGHT_SHADE","PSYCHIC"],"score":100},{"speciesId":"noivern","speciesName":"Noivern","rating":500,"matchups":[],"counters":[],"moves":{"fastMoves":[{"moveId":"AIR_SLASH","uses":11520},{"moveId":"BITE","uses":7180}],"chargedMoves":[{"moveId":"HURRICANE","uses":6252},{"moveId":"PSYCHIC","uses":5300},{"moveId":"DRACO_METEOR","uses":4777},{"moveId":"HEAT_WAVE","uses":2362}]},"moveset":["AIR_SLASH","DRACO_METEOR","HEAT_WAVE"],"score":100},{"speciesId":"octillery","speciesName":"Octillery","rating":500,"matchups":[],"counters":[],"moves":{"fastMoves":[{"moveId":"WATER_GUN","uses":9533},{"moveId":"MUD_SHOT","uses":9167}],"chargedMoves":[{"moveId":"OCTAZOOKA","uses":7476},{"moveId":"AURORA_BEAM","uses":4176},{"moveId":"GUNK_SHOT","uses":3733},{"moveId":"WATER_PULSE","uses":2256},{"moveId":"ACID_SPRAY","uses":1071}]},"moveset":["MUD_SHOT","ACID_SPRAY","AURORA_BEAM"],"score":100},{"speciesId":"omastar","speciesName":"Omastar","rating":500,"matchups":[],"counters":[],"moves":{"fastMoves":[{"moveId":"MUD_SHOT","uses":7010},{"moveId":"ROCK_THROW","uses":5857},{"moveId":"WATER_GUN","uses":5830}],"chargedMoves":[{"moveId":"ROCK_SLIDE","uses":6986},{"moveId":"ROCK_BLAST","uses":4989},{"moveId":"HYDRO_PUMP","uses":3184},{"moveId":"RETURN","uses":1944},{"moveId":"ANCIENT_POWER","uses":1591}]},"moveset":["MUD_SHOT","ANCIENT_POWER","HYDRO_PUMP"],"score":100},{"speciesId":"pelipper","speciesName":"Pelipper","rating":500,"matchups":[],"counters":[],"moves":{"fastMoves":[{"moveId":"WING_ATTACK","uses":9626},{"moveId":"WATER_GUN","uses":9074}],"chargedMoves":[{"moveId":"WEATHER_BALL_WATER","uses":11188},{"moveId":"HURRICANE","uses":3902},{"moveId":"BLIZZARD","uses":2388},{"moveId":"HYDRO_PUMP","uses":1245}]},"moveset":["WATER_GUN","BLIZZARD","HURRICANE"],"score":100},{"speciesId":"pidgeot","speciesName":"Pidgeot","rating":500,"matchups":[],"counters":[],"moves":{"fastMoves":[{"moveId":"GUST","uses":6178},{"moveId":"WING_ATTACK","uses":5520},{"moveId":"AIR_SLASH","uses":4312},{"moveId":"STEEL_WING","uses":2658}],"chargedMoves":[{"moveId":"BRAVE_BIRD","uses":11020},{"moveId":"AERIAL_ACE","uses":4483},{"moveId":"HURRICANE","uses":2056},{"moveId":"AIR_CUTTER","uses":1136}]},"moveset":["AIR_SLASH","AERIAL_ACE","AIR_CUTTER"],"score":100},{"speciesId":"piloswine","speciesName":"Piloswine","rating":500,"matchups":[],"counters":[],"moves":{"fastMoves":[{"moveId":"POWDER_SNOW","uses":11022},{"moveId":"ICE_SHARD","uses":7678}],"chargedMoves":[{"moveId":"AVALANCHE","uses":8938},{"moveId":"STONE_EDGE","uses":4425},{"moveId":"BULLDOZE","uses":3526},{"moveId":"RETURN","uses":1792}]},"moveset":["ICE_SHARD","AVALANCHE","BULLDOZE"],"score":100},{"speciesId":"pinsir","speciesName":"Pinsir","rating":500,"matchups":[],"counters":[],"moves":{"fastMoves":[{"moveId":"FURY_CUTTER","uses":9632},{"moveId":"BUG_BITE","uses":6542},{"moveId":"ROCK_SMASH","uses":2524}],"chargedMoves":[{"moveId":"CLOSE_COMBAT","uses":5836},{"moveId":"X_SCISSOR","uses":4691},{"moveId":"SUPER_POWER","uses":4333},{"moveId":"RETURN","uses":1658},{"moveId":"VICE_GRIP","uses":1495},{"moveId":"SUBMISSION","uses":698}]},"moveset":["BUG_BITE","CLOSE_COMBAT","RETURN"],"score":100},{"speciesId":"porygon_z","speciesName":"Porygon-Z","rating":500,"matchups":[],"counters":[],"moves":{"fastMoves":[{"moveId":"LOCK_ON","uses":2409},{"moveId":"HIDDEN_POWER_GROUND","uses":1114},{"moveId":"CHARGE_BEAM","uses":1092},{"moveId":"HIDDEN_POWER_ROCK","uses":1075},{"moveId":"HIDDEN_POWER_FIRE","uses":1029},{"moveId":"HIDDEN_POWER_FIGHTING","uses":1015},{"moveId":"HIDDEN_POWER_ICE","uses":1009},{"moveId":"HIDDEN_POWER_WATER","uses":1009},{"moveId":"HIDDEN_POWER_ELECTRIC","uses":975},{"moveId":"HIDDEN_POWER_FLYING","uses":973},{"moveId":"HIDDEN_POWER_GRASS","uses":948},{"moveId":"HIDDEN_POWER_DARK","uses":928},{"moveId":"HIDDEN_POWER_GHOST","uses":915},{"moveId":"HIDDEN_POWER_BUG","uses":872},{"moveId":"HIDDEN_POWER_PSYCHIC","uses":855},{"moveId":"HIDDEN_POWER_DRAGON","uses":830},{"moveId":"HIDDEN_POWER_STEEL","uses":814},{"moveId":"HIDDEN_POWER_POISON","uses":786}],"chargedMoves":[{"moveId":"TRI_ATTACK","uses":5952},{"moveId":"BLIZZARD","uses":3513},{"moveId":"ZAP_CANNON","uses":3013},{"moveId":"SOLAR_BEAM","uses":2904},{"moveId":"RETURN","uses":1860},{"moveId":"HYPER_BEAM","uses":1439}]},"moveset":["CHARGE_BEAM","BLIZZARD","HYPER_BEAM"],"score":100},{"speciesId":"porygon2","speciesName":"Porygon2","rating":500,"matchups":[],"counters":[],"moves":{"fastMoves":[{"moveId":"LOCK_ON","uses":1931},{"moveId":"HIDDEN_POWER_GROUND","uses":1140},{"moveId":"HIDDEN_POWER_ROCK","uses":1110},{"moveId":"HIDDEN_POWER_FIRE","uses":1066},{"moveId":"CHARGE_BEAM","uses":1049},{"moveId":"HIDDEN_POWER_FIGHTING","uses":1046},{"moveId":"HIDDEN_POWER_WATER","uses":1046},{"moveId":"HIDDEN_POWER_ICE","uses":1031},{"moveId":"HIDDEN_POWER_FLYING","uses":988},{"moveId":"HIDDEN_POWER_ELECTRIC","uses":987},{"moveId":"HIDDEN_POWER_GRASS","uses":974},{"moveId":"HIDDEN_POWER_DARK","uses":968},{"moveId":"HIDDEN_POWER_GHOST","uses":957},{"moveId":"HIDDEN_POWER_BUG","uses":898},{"moveId":"HIDDEN_POWER_PSYCHIC","uses":887},{"moveId":"HIDDEN_POWER_DRAGON","uses":871},{"moveId":"HIDDEN_POWER_STEEL","uses":858},{"moveId":"HIDDEN_POWER_POISON","uses":821}],"chargedMoves":[{"moveId":"TRI_ATTACK","uses":7415},{"moveId":"ZAP_CANNON","uses":3610},{"moveId":"SOLAR_BEAM","uses":3490},{"moveId":"RETURN","uses":2330},{"moveId":"HYPER_BEAM","uses":1812}]},"moveset":["CHARGE_BEAM","HYPER_BEAM","RETURN"],"score":100},{"speciesId":"probopass","speciesName":"Probopass","rating":500,"matchups":[],"counters":[],"moves":{"fastMoves":[{"moveId":"SPARK","uses":9557},{"moveId":"ROCK_THROW","uses":9143}],"chargedMoves":[{"moveId":"ROCK_SLIDE","uses":7848},{"moveId":"MAGNET_BOMB","uses":5497},{"moveId":"THUNDERBOLT","uses":3271},{"moveId":"RETURN","uses":2074}]},"moveset":["ROCK_THROW","MAGNET_BOMB","RETURN"],"score":100},{"speciesId":"pyroar","speciesName":"Pyroar","rating":500,"matchups":[],"counters":[],"moves":{"fastMoves":[{"moveId":"FIRE_FANG","uses":14825},{"moveId":"TAKE_DOWN","uses":3875}],"chargedMoves":[{"moveId":"FLAME_CHARGE","uses":6284},{"moveId":"OVERHEAT","uses":4842},{"moveId":"DARK_PULSE","uses":4632},{"moveId":"SOLAR_BEAM","uses":2944}]},"moveset":["FIRE_FANG","DARK_PULSE","FLAME_CHARGE"],"score":100},{"speciesId":"quagsire","speciesName":"Quagsire","rating":500,"matchups":[],"counters":[],"moves":{"fastMoves":[{"moveId":"MUD_SHOT","uses":10711},{"moveId":"WATER_GUN","uses":7989}],"chargedMoves":[{"moveId":"EARTHQUAKE","uses":6582},{"moveId":"STONE_EDGE","uses":5725},{"moveId":"SLUDGE_BOMB","uses":3750},{"moveId":"RETURN","uses":2361},{"moveId":"ACID_SPRAY","uses":285}]},"moveset":["MUD_SHOT","ACID_SPRAY","EARTHQUAKE"],"score":100},{"speciesId":"raichu","speciesName":"Raichu","rating":500,"matchups":[],"counters":[],"moves":{"fastMoves":[{"moveId":"VOLT_SWITCH","uses":6286},{"moveId":"THUNDER_SHOCK","uses":5307},{"moveId":"SPARK","uses":4620},{"moveId":"CHARM","uses":2496}],"chargedMoves":[{"moveId":"WILD_CHARGE","uses":7871},{"moveId":"THUNDER_PUNCH","uses":3833},{"moveId":"BRICK_BREAK","uses":3720},{"moveId":"SKULL_BASH","uses":2047},{"moveId":"THUNDER","uses":1238}]},"moveset":["CHARM","BRICK_BREAK","SKULL_BASH"],"score":100},{"speciesId":"raichu_alolan","speciesName":"Raichu (Alolan)","rating":500,"matchups":[],"counters":[],"moves":{"fastMoves":[{"moveId":"VOLT_SWITCH","uses":7224},{"moveId":"THUNDER_SHOCK","uses":6187},{"moveId":"SPARK","uses":5261}],"chargedMoves":[{"moveId":"WILD_CHARGE","uses":7888},{"moveId":"THUNDER_PUNCH","uses":3845},{"moveId":"GRASS_KNOT","uses":3488},{"moveId":"PSYCHIC","uses":3459}]},"moveset":["SPARK","GRASS_KNOT","PSYCHIC"],"score":100},{"speciesId":"rampardos","speciesName":"Rampardos","rating":500,"matchups":[],"counters":[],"moves":{"fastMoves":[{"moveId":"SMACK_DOWN","uses":16434},{"moveId":"ZEN_HEADBUTT","uses":2266}],"chargedMoves":[{"moveId":"ROCK_SLIDE","uses":9958},{"moveId":"FLAMETHROWER","uses":4786},{"moveId":"OUTRAGE","uses":3970}]},"moveset":["SMACK_DOWN","FLAMETHROWER","OUTRAGE"],"score":100},{"speciesId":"rapidash","speciesName":"Rapidash","rating":500,"matchups":[],"counters":[],"moves":{"fastMoves":[{"moveId":"INCINERATE","uses":7674},{"moveId":"FIRE_SPIN","uses":5001},{"moveId":"EMBER","uses":4800},{"moveId":"LOW_KICK","uses":1216}],"chargedMoves":[{"moveId":"DRILL_RUN","uses":8722},{"moveId":"FLAME_CHARGE","uses":7350},{"moveId":"FIRE_BLAST","uses":1663},{"moveId":"HEAT_WAVE","uses":1013}]},"moveset":["EMBER","DRILL_RUN","FIRE_BLAST"],"score":100},{"speciesId":"rapidash_galarian","speciesName":"Rapidash (Galarian)","rating":500,"matchups":[],"counters":[],"moves":{"fastMoves":[{"moveId":"PSYCHO_CUT","uses":15131},{"moveId":"LOW_KICK","uses":3569}],"chargedMoves":[{"moveId":"BODY_SLAM","uses":6948},{"moveId":"PSYCHIC","uses":4738},{"moveId":"MEGAHORN","uses":3890},{"moveId":"PLAY_ROUGH","uses":3129}]},"moveset":["LOW_KICK","BODY_SLAM","MEGAHORN"],"score":100},{"speciesId":"regice","speciesName":"Regice","rating":500,"matchups":[],"counters":[],"moves":{"fastMoves":[{"moveId":"LOCK_ON","uses":10149},{"moveId":"FROST_BREATH","uses":5643},{"moveId":"ROCK_SMASH","uses":2907}],"chargedMoves":[{"moveId":"BLIZZARD","uses":7220},{"moveId":"EARTHQUAKE","uses":6852},{"moveId":"FOCUS_BLAST","uses":4637}]},"moveset":["FROST_BREATH","BLIZZARD","EARTHQUAKE"],"score":100},{"speciesId":"relicanth","speciesName":"Relicanth","rating":500,"matchups":[],"counters":[],"moves":{"fastMoves":[{"moveId":"WATER_GUN","uses":15664},{"moveId":"ZEN_HEADBUTT","uses":3036}],"chargedMoves":[{"moveId":"AQUA_TAIL","uses":11170},{"moveId":"ANCIENT_POWER","uses":5763},{"moveId":"HYDRO_PUMP","uses":1728}]},"moveset":["WATER_GUN","ANCIENT_POWER","AQUA_TAIL"],"score":100},{"speciesId":"rhydon","speciesName":"Rhydon","rating":500,"matchups":[],"counters":[],"moves":{"fastMoves":[{"moveId":"MUD_SLAP","uses":13747},{"moveId":"ROCK_SMASH","uses":4953}],"chargedMoves":[{"moveId":"STONE_EDGE","uses":5835},{"moveId":"SURF","uses":5096},{"moveId":"EARTHQUAKE","uses":4339},{"moveId":"MEGAHORN","uses":3441}]},"moveset":["MUD_SLAP","EARTHQUAKE","MEGAHORN"],"score":100},{"speciesId":"rhyperior","speciesName":"Rhyperior","rating":500,"matchups":[],"counters":[],"moves":{"fastMoves":[{"moveId":"SMACK_DOWN","uses":10004},{"moveId":"MUD_SLAP","uses":8696}],"chargedMoves":[{"moveId":"ROCK_WRECKER","uses":6028},{"moveId":"SUPER_POWER","uses":3743},{"moveId":"SURF","uses":3242},{"moveId":"EARTHQUAKE","uses":2717},{"moveId":"STONE_EDGE","uses":1709},{"moveId":"SKULL_BASH","uses":1265}]},"moveset":["MUD_SLAP","EARTHQUAKE","ROCK_WRECKER"],"score":100},{"speciesId":"roserade","speciesName":"Roserade","rating":500,"matchups":[],"counters":[],"moves":{"fastMoves":[{"moveId":"BULLET_SEED","uses":7871},{"moveId":"POISON_JAB","uses":7109},{"moveId":"RAZOR_LEAF","uses":3739}],"chargedMoves":[{"moveId":"WEATHER_BALL_FIRE","uses":7488},{"moveId":"GRASS_KNOT","uses":5189},{"moveId":"SLUDGE_BOMB","uses":3597},{"moveId":"DAZZLING_GLEAM","uses":1330},{"moveId":"SOLAR_BEAM","uses":1102}]},"moveset":["BULLET_SEED","DAZZLING_GLEAM","GRASS_KNOT"],"score":100},{"speciesId":"sandslash_alolan","speciesName":"Sandslash (Alolan)","rating":500,"matchups":[],"counters":[],"moves":{"fastMoves":[{"moveId":"POWDER_SNOW","uses":12782},{"moveId":"METAL_CLAW","uses":5918}],"chargedMoves":[{"moveId":"ICE_PUNCH","uses":7736},{"moveId":"BLIZZARD","uses":3996},{"moveId":"BULLDOZE","uses":3942},{"moveId":"GYRO_BALL","uses":3027}]},"moveset":["METAL_CLAW","BLIZZARD","BULLDOZE"],"score":100},{"speciesId":"sceptile","speciesName":"Sceptile","rating":500,"matchups":[],"counters":[],"moves":{"fastMoves":[{"moveId":"BULLET_SEED","uses":9983},{"moveId":"FURY_CUTTER","uses":8717}],"chargedMoves":[{"moveId":"LEAF_BLADE","uses":7747},{"moveId":"DRAGON_CLAW","uses":3424},{"moveId":"FRENZY_PLANT","uses":2898},{"moveId":"EARTHQUAKE","uses":2366},{"moveId":"AERIAL_ACE","uses":2272}]},"moveset":["BULLET_SEED","AERIAL_ACE","DRAGON_CLAW"],"score":100},{"speciesId":"scizor","speciesName":"Scizor","rating":500,"matchups":[],"counters":[],"moves":{"fastMoves":[{"moveId":"FURY_CUTTER","uses":9543},{"moveId":"BULLET_PUNCH","uses":9157}],"chargedMoves":[{"moveId":"NIGHT_SLASH","uses":6965},{"moveId":"X_SCISSOR","uses":6019},{"moveId":"IRON_HEAD","uses":3617},{"moveId":"RETURN","uses":2104}]},"moveset":["BULLET_PUNCH","IRON_HEAD","NIGHT_SLASH"],"score":100},{"speciesId":"scolipede","speciesName":"Scolipede","rating":500,"matchups":[],"counters":[],"moves":{"fastMoves":[{"moveId":"POISON_JAB","uses":9949},{"moveId":"BUG_BITE","uses":8751}],"chargedMoves":[{"moveId":"X_SCISSOR","uses":6528},{"moveId":"MEGAHORN","uses":5218},{"moveId":"SLUDGE_BOMB","uses":4901},{"moveId":"GYRO_BALL","uses":2069}]},"moveset":["BUG_BITE","GYRO_BALL","MEGAHORN"],"score":100},{"speciesId":"scyther","speciesName":"Scyther","rating":500,"matchups":[],"counters":[],"moves":{"fastMoves":[{"moveId":"FURY_CUTTER","uses":8476},{"moveId":"AIR_SLASH","uses":6365},{"moveId":"STEEL_WING","uses":3857}],"chargedMoves":[{"moveId":"NIGHT_SLASH","uses":6388},{"moveId":"X_SCISSOR","uses":5351},{"moveId":"AERIAL_ACE","uses":3724},{"moveId":"RETURN","uses":1815},{"moveId":"BUG_BUZZ","uses":1387}]},"moveset":["AIR_SLASH","AERIAL_ACE","BUG_BUZZ"],"score":100},{"speciesId":"seaking","speciesName":"Seaking","rating":500,"matchups":[],"counters":[],"moves":{"fastMoves":[{"moveId":"WATERFALL","uses":7953},{"moveId":"POISON_JAB","uses":7160},{"moveId":"PECK","uses":3587}],"chargedMoves":[{"moveId":"DRILL_RUN","uses":6631},{"moveId":"ICY_WIND","uses":4985},{"moveId":"MEGAHORN","uses":3484},{"moveId":"WATER_PULSE","uses":2019},{"moveId":"ICE_BEAM","uses":1605}]},"moveset":["PECK","DRILL_RUN","ICE_BEAM"],"score":100},{"speciesId":"seismitoad","speciesName":"Seismitoad","rating":500,"matchups":[],"counters":[],"moves":{"fastMoves":[{"moveId":"MUD_SHOT","uses":10245},{"moveId":"BUBBLE","uses":8455}],"chargedMoves":[{"moveId":"EARTH_POWER","uses":7126},{"moveId":"MUDDY_WATER","uses":6719},{"moveId":"SLUDGE_BOMB","uses":4855}]},"moveset":["BUBBLE","EARTH_POWER","MUDDY_WATER"],"score":100},{"speciesId":"serperior","speciesName":"Serperior","rating":500,"matchups":[],"counters":[],"moves":{"fastMoves":[{"moveId":"VINE_WHIP","uses":15705},{"moveId":"IRON_TAIL","uses":2995}],"chargedMoves":[{"moveId":"GRASS_KNOT","uses":6937},{"moveId":"LEAF_TORNADO","uses":6717},{"moveId":"AERIAL_ACE","uses":5026}]},"moveset":["IRON_TAIL","AERIAL_ACE","GRASS_KNOT"],"score":100},{"speciesId":"shiftry","speciesName":"Shiftry","rating":500,"matchups":[],"counters":[],"moves":{"fastMoves":[{"moveId":"SNARL","uses":5997},{"moveId":"BULLET_SEED","uses":5797},{"moveId":"FEINT_ATTACK","uses":4136},{"moveId":"RAZOR_LEAF","uses":2775}],"chargedMoves":[{"moveId":"LEAF_BLADE","uses":8805},{"moveId":"FOUL_PLAY","uses":4516},{"moveId":"HURRICANE","uses":2234},{"moveId":"LEAF_TORNADO","uses":1697},{"moveId":"RETURN","uses":1473}]},"moveset":["BULLET_SEED","FOUL_PLAY","HURRICANE"],"score":100},{"speciesId":"simipour","speciesName":"Simipour","rating":500,"matchups":[],"counters":[],"moves":{"fastMoves":[{"moveId":"WATER_GUN","uses":12286},{"moveId":"BITE","uses":6414}],"chargedMoves":[{"moveId":"SURF","uses":10796},{"moveId":"CRUNCH","uses":6187},{"moveId":"HYDRO_PUMP","uses":1780}]},"moveset":["BITE","CRUNCH","HYDRO_PUMP"],"score":100},{"speciesId":"simisage","speciesName":"Simisage","rating":500,"matchups":[],"counters":[],"moves":{"fastMoves":[{"moveId":"VINE_WHIP","uses":13026},{"moveId":"BITE","uses":5674}],"chargedMoves":[{"moveId":"GRASS_KNOT","uses":8891},{"moveId":"CRUNCH","uses":7923},{"moveId":"SOLAR_BEAM","uses":1827}]},"moveset":["BITE","CRUNCH","GRASS_KNOT"],"score":100},{"speciesId":"simisear","speciesName":"Simisear","rating":500,"matchups":[],"counters":[],"moves":{"fastMoves":[{"moveId":"FIRE_SPIN","uses":12395},{"moveId":"BITE","uses":6305}],"chargedMoves":[{"moveId":"CRUNCH","uses":8345},{"moveId":"FLAMETHROWER","uses":8141},{"moveId":"FIRE_BLAST","uses":2157}]},"moveset":["BITE","CRUNCH","FIRE_BLAST"],"score":100},{"speciesId":"skuntank","speciesName":"Skuntank","rating":500,"matchups":[],"counters":[],"moves":{"fastMoves":[{"moveId":"POISON_JAB","uses":11206},{"moveId":"BITE","uses":7494}],"chargedMoves":[{"moveId":"CRUNCH","uses":7341},{"moveId":"SLUDGE_BOMB","uses":4914},{"moveId":"FLAMETHROWER","uses":4126},{"moveId":"RETURN","uses":2323}]},"moveset":["BITE","CRUNCH","FLAMETHROWER"],"score":100},{"speciesId":"slowbro","speciesName":"Slowbro","rating":500,"matchups":[],"counters":[],"moves":{"fastMoves":[{"moveId":"CONFUSION","uses":9621},{"moveId":"WATER_GUN","uses":9079}],"chargedMoves":[{"moveId":"PSYCHIC","uses":6527},{"moveId":"ICE_BEAM","uses":5277},{"moveId":"WATER_PULSE","uses":3707},{"moveId":"RETURN","uses":3202}]},"moveset":["CONFUSION","ICE_BEAM","PSYCHIC"],"score":100},{"speciesId":"slowking","speciesName":"Slowking","rating":500,"matchups":[],"counters":[],"moves":{"fastMoves":[{"moveId":"CONFUSION","uses":9620},{"moveId":"WATER_GUN","uses":9080}],"chargedMoves":[{"moveId":"PSYCHIC","uses":7337},{"moveId":"BLIZZARD","uses":4234},{"moveId":"FIRE_BLAST","uses":3607},{"moveId":"RETURN","uses":3533}]},"moveset":["CONFUSION","BLIZZARD","FIRE_BLAST"],"score":100},{"speciesId":"snorlax","speciesName":"Snorlax","rating":500,"matchups":[],"counters":[],"moves":{"fastMoves":[{"moveId":"LICK","uses":15569},{"moveId":"ZEN_HEADBUTT","uses":2635},{"moveId":"YAWN","uses":504}],"chargedMoves":[{"moveId":"BODY_SLAM","uses":5975},{"moveId":"SUPER_POWER","uses":4318},{"moveId":"EARTHQUAKE","uses":2327},{"moveId":"OUTRAGE","uses":1886},{"moveId":"HEAVY_SLAM","uses":1643},{"moveId":"SKULL_BASH","uses":1027},{"moveId":"RETURN","uses":869},{"moveId":"HYPER_BEAM","uses":664}]},"moveset":["LICK","BODY_SLAM","EARTHQUAKE"],"score":100},{"speciesId":"solrock","speciesName":"Solrock","rating":500,"matchups":[],"counters":[],"moves":{"fastMoves":[{"moveId":"CONFUSION","uses":9836},{"moveId":"ROCK_THROW","uses":8864}],"chargedMoves":[{"moveId":"ROCK_SLIDE","uses":10225},{"moveId":"PSYCHIC","uses":5471},{"moveId":"SOLAR_BEAM","uses":3002}]},"moveset":["CONFUSION","PSYCHIC","ROCK_SLIDE"],"score":100},{"speciesId":"spiritomb","speciesName":"Spiritomb","rating":500,"matchups":[],"counters":[],"moves":{"fastMoves":[{"moveId":"SUCKER_PUNCH","uses":9908},{"moveId":"FEINT_ATTACK","uses":8792}],"chargedMoves":[{"moveId":"SHADOW_BALL","uses":10037},{"moveId":"OMINOUS_WIND","uses":5358},{"moveId":"SHADOW_SNEAK","uses":3282}]},"moveset":["FEINT_ATTACK","OMINOUS_WIND","SHADOW_BALL"],"score":100},{"speciesId":"staraptor","speciesName":"Staraptor","rating":500,"matchups":[],"counters":[],"moves":{"fastMoves":[{"moveId":"WING_ATTACK","uses":10056},{"moveId":"QUICK_ATTACK","uses":8644}],"chargedMoves":[{"moveId":"BRAVE_BIRD","uses":9239},{"moveId":"CLOSE_COMBAT","uses":8370},{"moveId":"HEAT_WAVE","uses":1087}]},"moveset":["QUICK_ATTACK","BRAVE_BIRD","CLOSE_COMBAT"],"score":100},{"speciesId":"steelix","speciesName":"Steelix","rating":500,"matchups":[],"counters":[],"moves":{"fastMoves":[{"moveId":"DRAGON_TAIL","uses":8869},{"moveId":"THUNDER_FANG","uses":6782},{"moveId":"IRON_TAIL","uses":3052}],"chargedMoves":[{"moveId":"EARTHQUAKE","uses":6990},{"moveId":"CRUNCH","uses":6406},{"moveId":"HEAVY_SLAM","uses":5301}]},"moveset":["DRAGON_TAIL","CRUNCH","EARTHQUAKE"],"score":100},{"speciesId":"sudowoodo","speciesName":"Sudowoodo","rating":500,"matchups":[],"counters":[],"moves":{"fastMoves":[{"moveId":"COUNTER","uses":10880},{"moveId":"ROCK_THROW","uses":7820}],"chargedMoves":[{"moveId":"ROCK_SLIDE","uses":9661},{"moveId":"EARTHQUAKE","uses":5197},{"moveId":"STONE_EDGE","uses":3834}]},"moveset":["COUNTER","EARTHQUAKE","ROCK_SLIDE"],"score":100},{"speciesId":"suicune","speciesName":"Suicune","rating":500,"matchups":[],"counters":[],"moves":{"fastMoves":[{"moveId":"SNARL","uses":1628},{"moveId":"ICE_FANG","uses":1285},{"moveId":"HIDDEN_POWER_WATER","uses":1248},{"moveId":"EXTRASENSORY","uses":1198},{"moveId":"HIDDEN_POWER_GROUND","uses":1062},{"moveId":"HIDDEN_POWER_ROCK","uses":1020},{"moveId":"HIDDEN_POWER_FIGHTING","uses":973},{"moveId":"HIDDEN_POWER_FIRE","uses":972},{"moveId":"HIDDEN_POWER_ICE","uses":937},{"moveId":"HIDDEN_POWER_ELECTRIC","uses":918},{"moveId":"HIDDEN_POWER_FLYING","uses":902},{"moveId":"HIDDEN_POWER_GRASS","uses":887},{"moveId":"HIDDEN_POWER_DARK","uses":880},{"moveId":"HIDDEN_POWER_GHOST","uses":866},{"moveId":"HIDDEN_POWER_BUG","uses":815},{"moveId":"HIDDEN_POWER_PSYCHIC","uses":804},{"moveId":"HIDDEN_POWER_DRAGON","uses":792},{"moveId":"HIDDEN_POWER_STEEL","uses":768},{"moveId":"HIDDEN_POWER_POISON","uses":747}],"chargedMoves":[{"moveId":"ICE_BEAM","uses":5257},{"moveId":"HYDRO_PUMP","uses":4150},{"moveId":"RETURN","uses":3255},{"moveId":"BUBBLE_BEAM","uses":3087},{"moveId":"WATER_PULSE","uses":2974}]},"moveset":["EXTRASENSORY","BUBBLE_BEAM","HYDRO_PUMP"],"score":100},{"speciesId":"sunflora","speciesName":"Sunflora","rating":500,"matchups":[],"counters":[],"moves":{"fastMoves":[{"moveId":"BULLET_SEED","uses":10825},{"moveId":"RAZOR_LEAF","uses":7875}],"chargedMoves":[{"moveId":"SLUDGE_BOMB","uses":8097},{"moveId":"PETAL_BLIZZARD","uses":7556},{"moveId":"SOLAR_BEAM","uses":3041}]},"moveset":["BULLET_SEED","PETAL_BLIZZARD","SLUDGE_BOMB"],"score":100},{"speciesId":"swalot","speciesName":"Swalot","rating":500,"matchups":[],"counters":[],"moves":{"fastMoves":[{"moveId":"INFESTATION","uses":12779},{"moveId":"ROCK_SMASH","uses":5921}],"chargedMoves":[{"moveId":"SLUDGE_BOMB","uses":8419},{"moveId":"ICE_BEAM","uses":7460},{"moveId":"GUNK_SHOT","uses":2164},{"moveId":"ACID_SPRAY","uses":657}]},"moveset":["INFESTATION","ACID_SPRAY","GUNK_SHOT"],"score":100},{"speciesId":"talonflame","speciesName":"Talonflame","rating":500,"matchups":[],"counters":[],"moves":{"fastMoves":[{"moveId":"INCINERATE","uses":8333},{"moveId":"FIRE_SPIN","uses":5294},{"moveId":"PECK","uses":2677},{"moveId":"STEEL_WING","uses":2384}],"chargedMoves":[{"moveId":"BRAVE_BIRD","uses":9722},{"moveId":"FLAME_CHARGE","uses":5867},{"moveId":"HURRICANE","uses":1808},{"moveId":"FIRE_BLAST","uses":1325}]},"moveset":["FIRE_SPIN","BRAVE_BIRD","FIRE_BLAST"],"score":100},{"speciesId":"tangela","speciesName":"Tangela","rating":500,"matchups":[],"counters":[],"moves":{"fastMoves":[{"moveId":"VINE_WHIP","uses":11057},{"moveId":"INFESTATION","uses":7643}],"chargedMoves":[{"moveId":"GRASS_KNOT","uses":7766},{"moveId":"SLUDGE_BOMB","uses":5400},{"moveId":"POWER_WHIP","uses":3889},{"moveId":"SOLAR_BEAM","uses":1636}]},"moveset":["INFESTATION","GRASS_KNOT","POWER_WHIP"],"score":100},{"speciesId":"tangrowth","speciesName":"Tangrowth","rating":500,"matchups":[],"counters":[],"moves":{"fastMoves":[{"moveId":"VINE_WHIP","uses":11010},{"moveId":"INFESTATION","uses":7690}],"chargedMoves":[{"moveId":"POWER_WHIP","uses":6413},{"moveId":"ROCK_SLIDE","uses":6222},{"moveId":"SLUDGE_BOMB","uses":3263},{"moveId":"ANCIENT_POWER","uses":1428},{"moveId":"SOLAR_BEAM","uses":1352}]},"moveset":["INFESTATION","ANCIENT_POWER","POWER_WHIP"],"score":100},{"speciesId":"togekiss","speciesName":"Togekiss","rating":500,"matchups":[],"counters":[],"moves":{"fastMoves":[{"moveId":"AIR_SLASH","uses":1578},{"moveId":"CHARM","uses":1578},{"moveId":"HIDDEN_POWER_FLYING","uses":1247},{"moveId":"HIDDEN_POWER_GROUND","uses":1137},{"moveId":"HIDDEN_POWER_ROCK","uses":1086},{"moveId":"HIDDEN_POWER_FIRE","uses":1071},{"moveId":"HIDDEN_POWER_FIGHTING","uses":1038},{"moveId":"HIDDEN_POWER_WATER","uses":1020},{"moveId":"HIDDEN_POWER_ICE","uses":994},{"moveId":"HIDDEN_POWER_ELECTRIC","uses":976},{"moveId":"HIDDEN_POWER_DARK","uses":937},{"moveId":"HIDDEN_POWER_GHOST","uses":924},{"moveId":"HIDDEN_POWER_GRASS","uses":922},{"moveId":"HIDDEN_POWER_BUG","uses":863},{"moveId":"HIDDEN_POWER_PSYCHIC","uses":853},{"moveId":"HIDDEN_POWER_DRAGON","uses":837},{"moveId":"HIDDEN_POWER_STEEL","uses":819},{"moveId":"HIDDEN_POWER_POISON","uses":781}],"chargedMoves":[{"moveId":"AERIAL_ACE","uses":5615},{"moveId":"FLAMETHROWER","uses":5131},{"moveId":"ANCIENT_POWER","uses":4293},{"moveId":"DAZZLING_GLEAM","uses":3683}]},"moveset":["AIR_SLASH","AERIAL_ACE","ANCIENT_POWER"],"score":100},{"speciesId":"torterra","speciesName":"Torterra","rating":500,"matchups":[],"counters":[],"moves":{"fastMoves":[{"moveId":"RAZOR_LEAF","uses":11069},{"moveId":"BITE","uses":7631}],"chargedMoves":[{"moveId":"FRENZY_PLANT","uses":7223},{"moveId":"STONE_EDGE","uses":3984},{"moveId":"EARTHQUAKE","uses":3485},{"moveId":"SAND_TOMB","uses":1697},{"moveId":"RETURN","uses":1493},{"moveId":"SOLAR_BEAM","uses":810}]},"moveset":["BITE","EARTHQUAKE","FRENZY_PLANT"],"score":100},{"speciesId":"typhlosion","speciesName":"Typhlosion","rating":500,"matchups":[],"counters":[],"moves":{"fastMoves":[{"moveId":"INCINERATE","uses":7665},{"moveId":"SHADOW_CLAW","uses":6747},{"moveId":"EMBER","uses":4290}],"chargedMoves":[{"moveId":"BLAST_BURN","uses":11426},{"moveId":"SOLAR_BEAM","uses":3417},{"moveId":"OVERHEAT","uses":2443},{"moveId":"FIRE_BLAST","uses":1425}]},"moveset":["EMBER","BLAST_BURN","FIRE_BLAST"],"score":100},{"speciesId":"tyranitar","speciesName":"Tyranitar","rating":500,"matchups":[],"counters":[],"moves":{"fastMoves":[{"moveId":"SMACK_DOWN","uses":10592},{"moveId":"BITE","uses":6346},{"moveId":"IRON_TAIL","uses":1764}],"chargedMoves":[{"moveId":"STONE_EDGE","uses":7162},{"moveId":"CRUNCH","uses":6886},{"moveId":"FIRE_BLAST","uses":2387},{"moveId":"RETURN","uses":2265}]},"moveset":["BITE","CRUNCH","FIRE_BLAST"],"score":100},{"speciesId":"unfezant","speciesName":"Unfezant","rating":500,"matchups":[],"counters":[],"moves":{"fastMoves":[{"moveId":"AIR_SLASH","uses":11853},{"moveId":"STEEL_WING","uses":6847}],"chargedMoves":[{"moveId":"SKY_ATTACK","uses":12269},{"moveId":"HYPER_BEAM","uses":4131},{"moveId":"HEAT_WAVE","uses":2302}]},"moveset":["AIR_SLASH","HEAT_WAVE","HYPER_BEAM"],"score":100},{"speciesId":"ursaring","speciesName":"Ursaring","rating":500,"matchups":[],"counters":[],"moves":{"fastMoves":[{"moveId":"COUNTER","uses":7961},{"moveId":"SHADOW_CLAW","uses":7931},{"moveId":"METAL_CLAW","uses":2807}],"chargedMoves":[{"moveId":"CLOSE_COMBAT","uses":10388},{"moveId":"RETURN","uses":3966},{"moveId":"PLAY_ROUGH","uses":2825},{"moveId":"HYPER_BEAM","uses":1543}]},"moveset":["COUNTER","CLOSE_COMBAT","HYPER_BEAM"],"score":100},{"speciesId":"vaporeon","speciesName":"Vaporeon","rating":500,"matchups":[],"counters":[],"moves":{"fastMoves":[{"moveId":"WATER_GUN","uses":18700}],"chargedMoves":[{"moveId":"AQUA_TAIL","uses":11426},{"moveId":"LAST_RESORT","uses":4146},{"moveId":"HYDRO_PUMP","uses":1809},{"moveId":"WATER_PULSE","uses":1296}]},"moveset":["WATER_GUN","AQUA_TAIL","HYDRO_PUMP"],"score":100},{"speciesId":"venomoth","speciesName":"Venomoth","rating":500,"matchups":[],"counters":[],"moves":{"fastMoves":[{"moveId":"INFESTATION","uses":6297},{"moveId":"CONFUSION","uses":6291},{"moveId":"BUG_BITE","uses":6109}],"chargedMoves":[{"moveId":"POISON_FANG","uses":4994},{"moveId":"PSYCHIC","uses":4042},{"moveId":"BUG_BUZZ","uses":3887},{"moveId":"SILVER_WIND","uses":3422},{"moveId":"RETURN","uses":2357}]},"moveset":["BUG_BITE","BUG_BUZZ","POISON_FANG"],"score":100},{"speciesId":"vespiquen","speciesName":"Vespiquen","rating":500,"matchups":[],"counters":[],"moves":{"fastMoves":[{"moveId":"FURY_CUTTER","uses":5740},{"moveId":"BUG_BITE","uses":4899},{"moveId":"AIR_SLASH","uses":4606},{"moveId":"POISON_STING","uses":3439}],"chargedMoves":[{"moveId":"X_SCISSOR","uses":8559},{"moveId":"POWER_GEM","uses":4126},{"moveId":"SIGNAL_BEAM","uses":2369},{"moveId":"BUG_BUZZ","uses":2257},{"moveId":"FELL_STINGER","uses":1388}]},"moveset":["AIR_SLASH","BUG_BUZZ","FELL_STINGER"],"score":100},{"speciesId":"victreebel","speciesName":"Victreebel","rating":500,"matchups":[],"counters":[],"moves":{"fastMoves":[{"moveId":"RAZOR_LEAF","uses":11056},{"moveId":"ACID","uses":7644}],"chargedMoves":[{"moveId":"LEAF_BLADE","uses":9979},{"moveId":"SLUDGE_BOMB","uses":3932},{"moveId":"LEAF_TORNADO","uses":1913},{"moveId":"RETURN","uses":1786},{"moveId":"SOLAR_BEAM","uses":830},{"moveId":"ACID_SPRAY","uses":275}]},"moveset":["ACID","ACID_SPRAY","LEAF_BLADE"],"score":100},{"speciesId":"vileplume","speciesName":"Vileplume","rating":500,"matchups":[],"counters":[],"moves":{"fastMoves":[{"moveId":"RAZOR_LEAF","uses":10890},{"moveId":"ACID","uses":7810}],"chargedMoves":[{"moveId":"SLUDGE_BOMB","uses":5670},{"moveId":"PETAL_BLIZZARD","uses":4345},{"moveId":"MOONBLAST","uses":4161},{"moveId":"RETURN","uses":2762},{"moveId":"SOLAR_BEAM","uses":1779}]},"moveset":["ACID","MOONBLAST","PETAL_BLIZZARD"],"score":100},{"speciesId":"wailord","speciesName":"Wailord","rating":500,"matchups":[],"counters":[],"moves":{"fastMoves":[{"moveId":"WATER_GUN","uses":15984},{"moveId":"ZEN_HEADBUTT","uses":2716}],"chargedMoves":[{"moveId":"SURF","uses":12233},{"moveId":"BLIZZARD","uses":3879},{"moveId":"HYPER_BEAM","uses":2586}]},"moveset":["WATER_GUN","BLIZZARD","HYPER_BEAM"],"score":100},{"speciesId":"walrein","speciesName":"Walrein","rating":500,"matchups":[],"counters":[],"moves":{"fastMoves":[{"moveId":"WATERFALL","uses":10582},{"moveId":"FROST_BREATH","uses":8118}],"chargedMoves":[{"moveId":"EARTHQUAKE","uses":5996},{"moveId":"BLIZZARD","uses":5883},{"moveId":"RETURN","uses":3417},{"moveId":"WATER_PULSE","uses":3403}]},"moveset":["FROST_BREATH","BLIZZARD","EARTHQUAKE"],"score":100},{"speciesId":"weavile","speciesName":"Weavile","rating":500,"matchups":[],"counters":[],"moves":{"fastMoves":[{"moveId":"SNARL","uses":7586},{"moveId":"ICE_SHARD","uses":6337},{"moveId":"FEINT_ATTACK","uses":4788}],"chargedMoves":[{"moveId":"AVALANCHE","uses":8668},{"moveId":"FOUL_PLAY","uses":5574},{"moveId":"FOCUS_BLAST","uses":2668},{"moveId":"RETURN","uses":1801}]},"moveset":["FEINT_ATTACK","AVALANCHE","FOCUS_BLAST"],"score":100},{"speciesId":"weezing","speciesName":"Weezing","rating":500,"matchups":[],"counters":[],"moves":{"fastMoves":[{"moveId":"INFESTATION","uses":10071},{"moveId":"ACID","uses":5352},{"moveId":"TACKLE","uses":3280}],"chargedMoves":[{"moveId":"SLUDGE_BOMB","uses":4536},{"moveId":"SHADOW_BALL","uses":4259},{"moveId":"DARK_PULSE","uses":4069},{"moveId":"THUNDERBOLT","uses":3683},{"moveId":"RETURN","uses":2154}]},"moveset":["ACID","DARK_PULSE","RETURN"],"score":100},{"speciesId":"whimsicott","speciesName":"Whimsicott","rating":500,"matchups":[],"counters":[],"moves":{"fastMoves":[{"moveId":"CHARM","uses":9993},{"moveId":"RAZOR_LEAF","uses":8707}],"chargedMoves":[{"moveId":"GRASS_KNOT","uses":8179},{"moveId":"MOONBLAST","uses":6264},{"moveId":"HURRICANE","uses":4265}]},"moveset":["CHARM","GRASS_KNOT","HURRICANE"],"score":100},{"speciesId":"xatu","speciesName":"Xatu","rating":500,"matchups":[],"counters":[],"moves":{"fastMoves":[{"moveId":"AIR_SLASH","uses":10091},{"moveId":"FEINT_ATTACK","uses":8609}],"chargedMoves":[{"moveId":"AERIAL_ACE","uses":7274},{"moveId":"FUTURE_SIGHT","uses":6803},{"moveId":"OMINOUS_WIND","uses":4619}]},"moveset":["AIR_SLASH","AERIAL_ACE","FUTURE_SIGHT"],"score":100},{"speciesId":"yanmega","speciesName":"Yanmega","rating":500,"matchups":[],"counters":[],"moves":{"fastMoves":[{"moveId":"WING_ATTACK","uses":9887},{"moveId":"BUG_BITE","uses":8813}],"chargedMoves":[{"moveId":"AERIAL_ACE","uses":7031},{"moveId":"BUG_BUZZ","uses":6351},{"moveId":"ANCIENT_POWER","uses":5311}]},"moveset":["BUG_BITE","AERIAL_ACE","ANCIENT_POWER"],"score":100},{"speciesId":"zangoose","speciesName":"Zangoose","rating":500,"matchups":[],"counters":[],"moves":{"fastMoves":[{"moveId":"SHADOW_CLAW","uses":10613},{"moveId":"FURY_CUTTER","uses":8087}],"chargedMoves":[{"moveId":"CLOSE_COMBAT","uses":9452},{"moveId":"NIGHT_SLASH","uses":8055},{"moveId":"DIG","uses":1183}]},"moveset":["FURY_CUTTER","CLOSE_COMBAT","DIG"],"score":100},{"speciesId":"zapdos","speciesName":"Zapdos","rating":500,"matchups":[],"counters":[],"moves":{"fastMoves":[{"moveId":"THUNDER_SHOCK","uses":11985},{"moveId":"CHARGE_BEAM","uses":6715}],"chargedMoves":[{"moveId":"DRILL_PECK","uses":7621},{"moveId":"THUNDERBOLT","uses":3932},{"moveId":"ANCIENT_POWER","uses":2427},{"moveId":"RETURN","uses":1779},{"moveId":"THUNDER","uses":1720},{"moveId":"ZAP_CANNON","uses":1246}]},"moveset":["CHARGE_BEAM","ANCIENT_POWER","DRILL_PECK"],"score":100},{"speciesId":"zebstrika","speciesName":"Zebstrika","rating":500,"matchups":[],"counters":[],"moves":{"fastMoves":[{"moveId":"SPARK","uses":15540},{"moveId":"LOW_KICK","uses":3160}],"chargedMoves":[{"moveId":"WILD_CHARGE","uses":11002},{"moveId":"FLAME_CHARGE","uses":5359},{"moveId":"DISCHARGE","uses":2360}]},"moveset":["LOW_KICK","DISCHARGE","FLAME_CHARGE"],"score":100}]