{
    "presets": [{
        "pokemon": [{
            "speciesId": "diggersby",
            "fastMove": "MUD_SHOT",
            "chargedMoves": ["EARTHQUAKE", "FIRE_PUNCH"]
        }, {
            "speciesId": "froslass",
            "fastMove": "POWDER_SNOW",
            "chargedMoves": ["AVALANCHE", "SHADOW_BALL"]
        }, {
            "speciesId": "wigglytuff",
            "fastMove": "CHARM",
            "chargedMoves": ["ICE_BEAM", "PLAY_ROUGH"]
        }],
        "weight": 1
    }, {
        "pokemon": [{
            "speciesId": "cresselia",
            "fastMove": "PSYCHO_CUT",
            "chargedMoves": ["GRASS_KNOT", "MOONBLAST"]
        }, {
            "speciesId": "whiscash",
            "fastMove": "MUD_SHOT",
            "chargedMoves": ["MUD_BOMB", "BLIZZARD"]
        }, {
            "speciesId": "wigglytuff",
            "fastMove": "CHARM",
            "chargedMoves": ["ICE_BEAM", "PLAY_ROUGH"]
        }],
        "weight": 1
    }, {
        "pokemon": [{
            "speciesId": "zweilous",
            "fastMove": "DRAGON_BREATH",
            "chargedMoves": ["BODY_SLAM", "SLUDGE_BOMB"]
        }, {
            "speciesId": "froslass",
            "fastMove": "POWDER_SNOW",
            "chargedMoves": ["AVALANCHE", "SHADOW_BALL"]
        }, {
            "speciesId": "golbat",
            "fastMove": "WING_ATTACK",
            "chargedMoves": ["POISON_FANG", "SHADOW_BALL"]
        }],
        "weight": 1
    }, {
        "pokemon": [{
            "speciesId": "noctowl",
            "fastMove": "WING_ATTACK",
            "chargedMoves": ["SKY_ATTACK", "SHADOW_BALL"]
        }, {
            "speciesId": "diggersby",
            "fastMove": "MUD_SHOT",
            "chargedMoves": ["EARTHQUAKE", "FIRE_PUNCH"]
        }, {
            "speciesId": "registeel",
            "fastMove": "LOCK_ON",
            "chargedMoves": ["FOCUS_BLAST", "ZAP_CANNON"]
        }],
        "weight": 1
    }, {
        "pokemon": [{
            "speciesId": "wigglytuff",
            "fastMove": "CHARM",
            "chargedMoves": ["ICE_BEAM", "PLAY_ROUGH"]
        }, {
            "speciesId": "diggersby",
            "fastMove": "MUD_SHOT",
            "chargedMoves": ["EARTHQUAKE", "FIRE_PUNCH"]
        }, {
            "speciesId": "froslass",
            "fastMove": "POWDER_SNOW",
            "chargedMoves": ["AVALANCHE", "SHADOW_BALL"]
        }],
        "weight": 1
    }, {
        "pokemon": [{
            "speciesId": "froslass",
            "fastMove": "POWDER_SNOW",
            "chargedMoves": ["AVALANCHE", "SHADOW_BALL"]
        }, {
            "speciesId": "mandibuzz",
            "fastMove": "SNARL",
            "chargedMoves": ["FOUL_PLAY", "AERIAL_ACE"]
        }, {
            "speciesId": "wigglytuff",
            "fastMove": "CHARM",
            "chargedMoves": ["ICE_BEAM", "PLAY_ROUGH"]
        }],
        "weight": 1
    }, {
        "pokemon": [{
            "speciesId": "cresselia",
            "fastMove": "PSYCHO_CUT",
            "chargedMoves": ["GRASS_KNOT", "MOONBLAST"]
        }, {
            "speciesId": "noctowl",
            "fastMove": "WING_ATTACK",
            "chargedMoves": ["SKY_ATTACK", "SHADOW_BALL"]
        }, {
            "speciesId": "registeel",
            "fastMove": "LOCK_ON",
            "chargedMoves": ["FOCUS_BLAST", "ZAP_CANNON"]
        }],
        "weight": 1
    }, {
        "pokemon": [{
            "speciesId": "beedrill",
            "fastMove": "POISON_JAB",
            "chargedMoves": ["X_SCISSOR", "DRILL_RUN"]
        }, {
            "speciesId": "mandibuzz",
            "fastMove": "SNARL",
            "chargedMoves": ["FOUL_PLAY", "AERIAL_ACE"]
        }, {
            "speciesId": "zweilous",
            "fastMove": "DRAGON_BREATH",
            "chargedMoves": ["BODY_SLAM", "DARK_PULSE"]
        }],
        "weight": 1
    }, {
        "pokemon": [{
            "speciesId": "whiscash",
            "fastMove": "MUD_SHOT",
            "chargedMoves": ["MUD_BOMB", "BLIZZARD"]
        }, {
            "speciesId": "noctowl",
            "fastMove": "WING_ATTACK",
            "chargedMoves": ["SKY_ATTACK", "SHADOW_BALL"]
        }, {
            "speciesId": "registeel",
            "fastMove": "LOCK_ON",
            "chargedMoves": ["FOCUS_BLAST", "ZAP_CANNON"]
        }],
        "weight": 1
    }, {
        "pokemon": [{
            "speciesId": "froslass",
            "fastMove": "POWDER_SNOW",
            "chargedMoves": ["AVALANCHE", "SHADOW_BALL"]
        }, {
            "speciesId": "diggersby",
            "fastMove": "MUD_SHOT",
            "chargedMoves": ["EARTHQUAKE", "FIRE_PUNCH"]
        }, {
            "speciesId": "whiscash",
            "fastMove": "MUD_SHOT",
            "chargedMoves": ["MUD_BOMB", "BLIZZARD"]
        }],
        "weight": 1
    }, {
        "pokemon": [{
            "speciesId": "diggersby",
            "fastMove": "MUD_SHOT",
            "chargedMoves": ["EARTHQUAKE", "FIRE_PUNCH"]
        }, {
            "speciesId": "cresselia",
            "fastMove": "PSYCHO_CUT",
            "chargedMoves": ["GRASS_KNOT", "MOONBLAST"]
        }, {
            "speciesId": "froslass",
            "fastMove": "POWDER_SNOW",
            "chargedMoves": ["AVALANCHE", "SHADOW_BALL"]
        }],
        "weight": 1
    }, {
        "pokemon": [{
            "speciesId": "whiscash",
            "fastMove": "MUD_SHOT",
            "chargedMoves": ["MUD_BOMB", "BLIZZARD"]
        }, {
            "speciesId": "abomasnow",
            "fastMove": "POWDER_SNOW",
            "chargedMoves": ["WEATHER_BALL_ICE", "ENERGY_BALL"]
        }, {
            "speciesId": "machamp",
            "fastMove": "COUNTER",
            "chargedMoves": ["CROSS_CHOP", "ROCK_SLIDE"],
            "shadowType": "shadow"
        }],
        "weight": 1
    }, {
        "pokemon": [{
            "speciesId": "whiscash",
            "fastMove": "MUD_SHOT",
            "chargedMoves": ["MUD_BOMB", "BLIZZARD"]
        }, {
            "speciesId": "granbull",
            "fastMove": "CHARM",
            "chargedMoves": ["CLOSE_COMBAT", "CRUNCH"],
            "shadowType": "shadow"
        }, {
            "speciesId": "wigglytuff",
            "fastMove": "CHARM",
            "chargedMoves": ["ICE_BEAM", "PLAY_ROUGH"]
        }],
        "weight": 1
    }, {
        "pokemon": [{
            "speciesId": "machamp",
            "fastMove": "COUNTER",
            "chargedMoves": ["CROSS_CHOP", "ROCK_SLIDE"],
            "shadowType": "shadow"
        }, {
            "speciesId": "diggersby",
            "fastMove": "MUD_SHOT",
            "chargedMoves": ["EARTHQUAKE", "FIRE_PUNCH"]
        }, {
            "speciesId": "marowak_alolan_shadow",
            "fastMove": "FIRE_SPIN",
            "chargedMoves": ["BONE_CLUB", "SHADOW_BONE"]
        }],
        "weight": 1
    }, {
        "pokemon": [{
            "speciesId": "whiscash",
            "fastMove": "MUD_SHOT",
            "chargedMoves": ["MUD_BOMB", "BLIZZARD"]
        },  {
            "speciesId": "marowak_alolan_shadow",
            "fastMove": "FIRE_SPIN",
            "chargedMoves": ["BONE_CLUB", "SHADOW_BONE"]
        }, {
            "speciesId": "ninetales",
            "fastMove": "FIRE_SPIN",
            "chargedMoves": ["WEATHER_BALL_FIRE", "OVERHEAT"],
            "shadowType": "shadow"
        }],
        "weight": 1
    }, {
        "pokemon": [{
            "speciesId": "araquanid",
            "fastMove": "BUG_BITE",
            "chargedMoves": ["BUBBLE_BEAM", "BUG_BUZZ"]
        },  {
            "speciesId": "registeel",
            "fastMove": "LOCK_ON",
            "chargedMoves": ["FOCUS_BLAST", "ZAP_CANNON"]
        }, {
            "speciesId": "lickitung",
            "fastMove": "LICK",
            "chargedMoves": ["BODY_SLAM", "POWER_WHIP"]
        }],
        "weight": 1
    }]
}
